[
 {
  "instituicao": "PREFEITURA MUNICIPAL DO NATAL",
  "orgao": "SECRETARIA MUNICIPAL DE SAUDE",
  "credor": "08.241.747/0001-43 - PREFEITURA MUNICIPAL DE NATAL",
  "empenhado": "R$ 2.000.000,00",
  "anulado": "R$ 575.281,57",
  "liquidado": "R$ 1.424.718,43",
  "pago": "R$ 575.281,57",
  "elemento": "VENCIMENTOS E VANTAGENS FIXAS - PESSOAL CIVIL",
  "numero": "204901599 / 2014",
  "data": "29/12/2014",
  "historico": "Complementação do empenho nº 215, no que tange a folha de pagamento no exercício 2014.",
  "itens": [
   {
    "descricao": "CONVERSAO",
    "quantidade": "1.00",
    "valor_unitario": "2.000.000,00",
    "valor_total": "2.000.000,00"
   }
  ]
 },
 {
  "instituicao": "PREFEITURA MUNICIPAL DO NATAL",
  "orgao": "SECRETARIA MUNICIPAL DE SAUDE",
  "credor": "08.241.747/0001-43 - PREFEITURA MUNICIPAL DE NATAL",
  "empenhado": "R$ 26.000.000,00",
  "anulado": "R$ 3.451.088,86",
  "liquidado": "R$ 22.548.911,14",
  "pago": "R$ 3.451.088,86",
  "elemento": "VENCIMENTOS E VANTAGENS FIXAS - PESSOAL CIVIL",
  "numero": "204901598 / 2014",
  "data": "29/12/2014",
  "historico": "Complementação do empenho nº 186, no que tange as despesas vencimentos e vantagens fixas-pessoal.",
  "itens": [
   {
    "descricao": "CONVERSAO",
    "quantidade": "1.00",
    "valor_unitario": "26.000.000,00",
    "valor_total": "26.000.000,00"
   }
  ]
 },
 {
  "instituicao": "PREFEITURA MUNICIPAL DO NATAL",
  "orgao": "SECRETARIA MUNICIPAL DE SAUDE",
  "credor": "08.241.747/0001-43 - PREFEITURA MUNICIPAL DE NATAL",
  "empenhado": "R$ 9.000.000,00",
  "anulado": "R$ 819.780,17",
  "liquidado": "R$ 8.180.219,83",
  "pago": "R$ 819.780,17",
  "elemento": "VENCIMENTOS E VANTAGENS FIXAS - PESSOAL CIVIL",
  "numero": "204901597 / 2014",
  "data": "29/12/2014",
  "historico": "Complementação do empenho nº 676, no que tange ao 13º salário.",
  "itens": [
   {
    "descricao": "CONVERSAO",
    "quantidade": "1.00",
    "valor_unitario": "9.000.000,00",
    "valor_total": "9.000.000,00"
   }
  ]
 },
 {
  "instituicao": "PREFEITURA MUNICIPAL DO NATAL",
  "orgao": "SECRETARIA MUNICIPAL DE SAUDE",
  "credor": "08.241.747/0001-43 - PREFEITURA MUNICIPAL DE NATAL",
  "empenhado": "R$ 6.310.000,00",
  "anulado": "R$ 1.245,71",
  "liquidado": "R$ 6.308.754,29",
  "pago": "R$ 1.245,71",
  "elemento": "VENCIMENTOS E VANTAGENS FIXAS - PESSOAL CIVIL",
  "numero": "204901291 / 2014",
  "data": "30/10/2014",
  "historico": "O presente instrumento tem por objeto a complementação do empenho n° 186, no que tange as despesas vencimentos e vantagens fixas-pessoal, conforme autos do processo.",
  "itens": [
   {
    "descricao": "CONVERSAO",
    "quantidade": "1.00",
    "valor_unitario": "6.310.000,00",
    "valor_total": "6.310.000,00"
   }
  ]
 },
 {
  "instituicao": "PREFEITURA MUNICIPAL DO NATAL",
  "orgao": "SECRETARIA MUNICIPAL DE SAUDE",
  "credor": "08.241.747/0001-43 - PREFEITURA MUNICIPAL DE NATAL",
  "empenhado": "R$ 7.692.000,00",
  "anulado": "R$ 6.574.394,01",
  "liquidado": "R$ 1.117.605,99",
  "pago": "R$ 6.574.394,01",
  "elemento": "VENCIMENTOS E VANTAGENS FIXAS - PESSOAL CIVIL",
  "numero": "204900833 / 2014",
  "data": "30/07/2014",
  "historico": "Complementação a nota de empenho 00.215/2014.",
  "itens": [
   {
    "descricao": "CONVERSAO",
    "quantidade": "1.00",
    "valor_unitario": "7.692.000,00",
    "valor_total": "7.692.000,00"
   }
  ]
 },
 {
  "instituicao": "PREFEITURA MUNICIPAL DO NATAL",
  "orgao": "SECRETARIA MUNICIPAL DE SAUDE",
  "credor": "08.241.747/0001-43 - PREFEITURA MUNICIPAL DE NATAL",
  "empenhado": "R$ 5.400.000,00",
  "anulado": "R$ 7.508,53",
  "liquidado": "R$ 5.392.491,47",
  "pago": "R$ 7.508,53",
  "elemento": "VENCIMENTOS E VANTAGENS FIXAS - PESSOAL CIVIL",
  "numero": "204900676 / 2014",
  "data": "12/06/2014",
  "historico": "Referente ao 13º Salario.",
  "itens": [
   {
    "descricao": "CONVERSAO",
    "quantidade": "1.00",
    "valor_unitario": "5.400.000,00",
    "valor_total": "5.400.000,00"
   }
  ]
 },
 {
  "instituicao": "PREFEITURA MUNICIPAL DO NATAL",
  "orgao": "SECRETARIA MUNICIPAL DE SAUDE",
  "credor": "08.241.747/0001-43 - PREFEITURA MUNICIPAL DE NATAL",
  "empenhado": "R$ 5.457.000,00",
  "anulado": "R$ 67.730,97",
  "liquidado": "R$ 5.389.269,03",
  "pago": "R$ 67.730,97",
  "elemento": "VENCIMENTOS E VANTAGENS FIXAS - PESSOAL CIVIL",
  "numero": "204900215 / 2014",
  "data": "31/01/2014",
  "historico": "Referente a despesas com folha de pagamento no exercício de 2014.",
  "itens": [
   {
    "descricao": "CONVERSAO",
    "quantidade": "1.00",
    "valor_unitario": "5.457.000,00",
    "valor_total": "5.457.000,00"
   }
  ]
 },
 {
  "instituicao": "PREFEITURA MUNICIPAL DO NATAL",
  "orgao": "SECRETARIA MUNICIPAL DE SAUDE",
  "credor": "08.241.747/0001-43 - PREFEITURA MUNICIPAL DE NATAL",
  "empenhado": "R$ 3.515,38",
  "anulado": "R$ 0,00",
  "liquidado": "R$ 3.515,38",
  "pago": "R$ 0,00",
  "elemento": "VENCIMENTOS E VANTAGENS FIXAS - PESSOAL CIVIL",
  "numero": "204900210 / 2014",
  "data": "31/01/2014",
  "historico": "Referente ao 13º folha de jan/2014.",
  "itens": [
   {
    "descricao": "CONVERSAO",
    "quantidade": "1.00",
    "valor_unitario": "3.515,38",
    "valor_total": "3.515,38"
   }
  ]
 },
 {
  "instituicao": "PREFEITURA MUNICIPAL DO NATAL",
  "orgao": "SECRETARIA MUNICIPAL DE SAUDE",
  "credor": "08.241.747/0001-43 - PREFEITURA MUNICIPAL DE NATAL",
  "empenhado": "R$ 1.000.000,00",
  "anulado": "R$ 0,00",
  "liquidado": "R$ 1.000.000,00",
  "pago": "R$ 0,00",
  "elemento": "VENCIMENTOS E VANTAGENS FIXAS - PESSOAL CIVIL",
  "numero": "204900209 / 2014",
  "data": "31/01/2014",
  "historico": "O presente instrumento tem por objetivo as despesas com vencimentos e vantagens fixas-pessoal, valor empenhado conforme disponibilidade orçamentaria do momento.",
  "itens": [
   {
    "descricao": "CONVERSAO",
    "quantidade": "1.00",
    "valor_unitario": "1.000.000,00",
    "valor_total": "1.000.000,00"
   }
  ]
 },
 {
  "instituicao": "PREFEITURA MUNICIPAL DO NATAL",
  "orgao": "SECRETARIA MUNICIPAL DE SAUDE",
  "credor": "08.241.747/0001-43 - PREFEITURA MUNICIPAL DE NATAL",
  "empenhado": "R$ 26.754.000,00",
  "anulado": "R$ 7.841.020,00",
  "liquidado": "R$ 18.912.980,00",
  "pago": "R$ 7.841.020,00",
  "elemento": "VENCIMENTOS E VANTAGENS FIXAS - PESSOAL CIVIL",
  "numero": "204900208 / 2014",
  "data": "31/01/2014",
  "historico": "O presente instrumento tem por objetivo as despesas com vencimentos e vantagens fixas-pessoal, valor empenhado conforme disponibilidade orçamentaria do momento.",
  "itens": [
   {
    "descricao": "CONVERSAO",
    "quantidade": "1.00",
    "valor_unitario": "26.754.000,00",
    "valor_total": "26.754.000,00"
   }
  ]
 },
 {
  "instituicao": "PREFEITURA MUNICIPAL DO NATAL",
  "orgao": "SECRETARIA MUNICIPAL DE SAUDE",
  "credor": "000.000.000-00 - SEMIRAMES DANTAS",
  "empenhado": "R$ 590,41",
  "anulado": "R$ 590,41",
  "liquidado": "R$ 0,00",
  "pago": "R$ 590,41",
  "elemento": "VENCIMENTOS E VANTAGENS FIXAS - PESSOAL CIVIL",
  "numero": "204901106 / 2014",
  "data": "17/09/2014",
  "historico": "O presente instrumento requer o pagamento, conforme Requerimento do Servidor anexo na folha 01 dos autos.",
  "itens": [
   {
    "descricao": "CONVERSAO",
    "quantidade": "1.00",
    "valor_unitario": "590,41",
    "valor_total": "590,41"
   }
  ]
 },
 {
  "instituicao": "PREFEITURA MUNICIPAL DO NATAL",
  "orgao": "SECRETARIA MUNICIPAL DE SAUDE",
  "credor": "02.800.122/0001-98 - CIRURGICA BEZERRA DISTRIBUIDORA LTDA",
  "empenhado": "R$ 214.416,00",
  "anulado": "R$ 0,00",
  "liquidado": "R$ 2.778,00",
  "pago": "R$ 0,00",
  "elemento": "SENTENCAS JUDICIAIS",
  "numero": "204901185 / 2014",
  "data": "30/09/2014",
  "historico": "O presente instrumento tem por objeto a aquisição de produtos formulados: nutrição e oral - alimentação especializada, conforme contrato firmado.",
  "itens": [
   {
    "descricao": "CONVERSAO",
    "quantidade": "1.00",
    "valor_unitario": "214.416,00",
    "valor_total": "214.416,00"
   }
  ]
 },
 {
  "instituicao": "PREFEITURA MUNICIPAL DO NATAL",
  "orgao": "SECRETARIA MUNICIPAL DE SAUDE",
  "credor": "35.291.038/0001-45 - W.T. COMERCIO E REPRESENTAÇÃO LTDA",
  "empenhado": "R$ 235.568,00",
  "anulado": "R$ 0,00",
  "liquidado": "R$ 235.568,00",
  "pago": "R$ 0,00",
  "elemento": "SENTENCAS JUDICIAIS",
  "numero": "204901277 / 2014",
  "data": "24/10/2014",
  "historico": "O presente instrumento tem por objeto a aquisição de formulas, alimentação especializada, observando o Contrato firmado entre as partes.",
  "itens": [
   {
    "descricao": "CONVERSAO",
    "quantidade": "1.00",
    "valor_unitario": "235.568,00",
    "valor_total": "235.568,00"
   }
  ]
 },
 {
  "instituicao": "PREFEITURA MUNICIPAL DO NATAL",
  "orgao": "SECRETARIA MUNICIPAL DE SAUDE",
  "credor": "08.241.747/0001-43 - PREFEITURA MUNICIPAL DE NATAL",
  "empenhado": "R$ 78.000,00",
  "anulado": "R$ 8.934,10",
  "liquidado": "R$ 69.065,90",
  "pago": "R$ 8.934,10",
  "elemento": "SALARIO-FAMILIA",
  "numero": "204900188 / 2014",
  "data": "31/01/2014",
  "historico": "O presente tem por objetivo as despesas com salario familia, conforme memorando anexado nos autos a pagina 01, com origem do DGTES/SGRTS sendo esse assinado por sua Diretora. Valor empenhado conforme disponibilidade orçamentaria do momento.",
  "itens": [
   {
    "descricao": "CONVERSAO",
    "quantidade": "1.00",
    "valor_unitario": "78.000,00",
    "valor_total": "78.000,00"
   }
  ]
 },
 {
  "instituicao": "PREFEITURA MUNICIPAL DO NATAL",
  "orgao": "SECRETARIA MUNICIPAL DE SAUDE",
  "credor": "24.365.710/0001-83 - UNIVERSIDADE FEDERAL DO RIO G. DO NORTE",
  "empenhado": "R$ 64.000,00",
  "anulado": "R$ 0,00",
  "liquidado": "R$ 6.383,66",
  "pago": "R$ 0,00",
  "elemento": "RESSARCIMENTO DE DESPESAS  DE PESSOAL REQUISITADO",
  "numero": "204901294 / 2014",
  "data": "29/10/2014",
  "historico": "O presente instrumento tem por objeto a complementação do empenho nº 401/2014, no que tange ao ressarcimento do valor da remuneração do servidor Cipriano Maia de Vasconcelos.",
  "itens": [
   {
    "descricao": "CONVERSAO",
    "quantidade": "1.00",
    "valor_unitario": "64.000,00",
    "valor_total": "64.000,00"
   }
  ]
 },
 {
  "instituicao": "PREFEITURA MUNICIPAL DO NATAL",
  "orgao": "SECRETARIA MUNICIPAL DE SAUDE",
  "credor": "24.365.710/0001-83 - UNIVERSIDADE FEDERAL DO RIO G. DO NORTE",
  "empenhado": "R$ 166.188,77",
  "anulado": "R$ 0,00",
  "liquidado": "R$ 166.188,77",
  "pago": "R$ 0,00",
  "elemento": "RESSARCIMENTO DE DESPESAS  DE PESSOAL REQUISITADO",
  "numero": "204900401 / 2014",
  "data": "13/03/2014",
  "historico": "Referente ao ressarcimento do valor da remuneração do servidor Cipriano Maia de Vasconcelos, aos meses de janeiro a dezembro 2014 incluindo 13° salário.",
  "itens": [
   {
    "descricao": "CONVERSAO",
    "quantidade": "1.00",
    "valor_unitario": "166.188,77",
    "valor_total": "166.188,77"
   }
  ]
 },
 {
  "instituicao": "PREFEITURA MUNICIPAL DO NATAL",
  "orgao": "SECRETARIA MUNICIPAL DE SAUDE",
  "credor": "24.365.710/0001-83 - UNIVERSIDADE FEDERAL DO RIO G. DO NORTE",
  "empenhado": "R$ 106.806,71",
  "anulado": "R$ 0,00",
  "liquidado": "R$ 90.670,00",
  "pago": "R$ 0,00",
  "elemento": "RESSARCIMENTO DE DESPESAS  DE PESSOAL REQUISITADO",
  "numero": "204900400 / 2014",
  "data": "13/03/2014",
  "historico": "Referente ao ressarcimento do valor da remuneração da servidora Miranice Nunes dos Santos referente aos meses de janeiro a dezembro de 2014 incluindo 13º salário.",
  "itens": []
 },
 {
  "instituicao": "PREFEITURA MUNICIPAL DO NATAL",
  "orgao": "SECRETARIA MUNICIPAL DE SAUDE",
  "credor": "12.747.465/0001-90 - HARABELLO PASSAGENS E TURISMO LTDA.",
  "empenhado": "R$ 12.184,62",
  "anulado": "R$ 8.708,34",
  "liquidado": "R$ 3.476,28",
  "pago": "R$ 8.708,34",
  "elemento": "PASSAGENS E DESPESAS COM LOCOMOCAO",
  "numero": "204900370 / 2014",
  "data": "27/02/2014",
  "historico": "Fornecimento de passagens aéreas, solicitado no memo de n.º 43/2013 - SAD-AIS, autorizado pelo Titular da Pasta da SMS às folhas 01 do Processo em questão.",
  "itens": [
   {
    "descricao": "CONVERSAO",
    "quantidade": "1.00",
    "valor_unitario": "12.184,62",
    "valor_total": "12.184,62"
   }
  ]
 },
 {
  "instituicao": "PREFEITURA MUNICIPAL DO NATAL",
  "orgao": "SECRETARIA MUNICIPAL DE SAUDE",
  "credor": "12.747.465/0001-90 - HARABELLO PASSAGENS E TURISMO LTDA.",
  "empenhado": "R$ 73.333,32",
  "anulado": "R$ 58.760,71",
  "liquidado": "R$ 14.572,61",
  "pago": "R$ 58.760,71",
  "elemento": "PASSAGENS E DESPESAS COM LOCOMOCAO",
  "numero": "204900247 / 2014",
  "data": "20/01/2014",
  "historico": "Fornecimento de passagens aéreas.",
  "itens": []
 },
 {
  "instituicao": "PREFEITURA MUNICIPAL DO NATAL",
  "orgao": "SECRETARIA MUNICIPAL DE SAUDE",
  "credor": "12.747.465/0001-90 - HARABELLO PASSAGENS E TURISMO LTDA.",
  "empenhado": "R$ 45.000,00",
  "anulado": "R$ 45.000,00",
  "liquidado": "R$ 0,00",
  "pago": "R$ 45.000,00",
  "elemento": "PASSAGENS E DESPESAS COM LOCOMOCAO",
  "numero": "204900246 / 2014",
  "data": "31/01/2014",
  "historico": "Forneciemento de passagens aereas.",
  "itens": [
   {
    "descricao": "CONVERSAO",
    "quantidade": "1.00",
    "valor_unitario": "45.000,00",
    "valor_total": "45.000,00"
   }
  ]
 },
 {
  "instituicao": "PREFEITURA MUNICIPAL DO NATAL",
  "orgao": "SECRETARIA MUNICIPAL DE SAUDE",
  "credor": "12.747.465/0001-90 - HARABELLO PASSAGENS E TURISMO LTDA.",
  "empenhado": "R$ 21.435,90",
  "anulado": "R$ 14.177,95",
  "liquidado": "R$ 7.257,95",
  "pago": "R$ 14.177,95",
  "elemento": "PASSAGENS E DESPESAS COM LOCOMOCAO",
  "numero": "204900244 / 2014",
  "data": "20/01/2014",
  "historico": "Fornecimento de passagens aéreas.",
  "itens": [
   {
    "descricao": "CONVERSAO",
    "quantidade": "1.00",
    "valor_unitario": "21.435,90",
    "valor_total": "21.435,90"
   }
  ]
 },
 {
  "instituicao": "PREFEITURA MUNICIPAL DO NATAL",
  "orgao": "SECRETARIA MUNICIPAL DE SAUDE",
  "credor": "12.747.465/0001-90 - HARABELLO PASSAGENS E TURISMO LTDA.",
  "empenhado": "R$ 36.666,67",
  "anulado": "R$ 25.911,27",
  "liquidado": "R$ 10.755,40",
  "pago": "R$ 25.911,27",
  "elemento": "PASSAGENS E DESPESAS COM LOCOMOCAO",
  "numero": "204900243 / 2014",
  "data": "31/01/2014",
  "historico": "Forneciemento de passagens aereas.",
  "itens": [
   {
    "descricao": "CONVERSAO",
    "quantidade": "1.00",
    "valor_unitario": "36.666,67",
    "valor_total": "36.666,67"
   }
  ]
 },
 {
  "instituicao": "PREFEITURA MUNICIPAL DO NATAL",
  "orgao": "SECRETARIA MUNICIPAL DE SAUDE",
  "credor": "12.747.465/0001-90 - HARABELLO PASSAGENS E TURISMO LTDA.",
  "empenhado": "R$ 11.056,41",
  "anulado": "R$ 11.056,41",
  "liquidado": "R$ 0,00",
  "pago": "R$ 11.056,41",
  "elemento": "PASSAGENS E DESPESAS COM LOCOMOCAO",
  "numero": "204900242 / 2014",
  "data": "31/01/2014",
  "historico": "Forneciemento de passagens aereas.",
  "itens": [
   {
    "descricao": "CONVERSAO",
    "quantidade": "1.00",
    "valor_unitario": "11.056,41",
    "valor_total": "11.056,41"
   }
  ]
 },
 {
  "instituicao": "PREFEITURA MUNICIPAL DO NATAL",
  "orgao": "SECRETARIA MUNICIPAL DE SAUDE",
  "credor": "12.747.465/0001-90 - HARABELLO PASSAGENS E TURISMO LTDA.",
  "empenhado": "R$ 3.723,08",
  "anulado": "R$ 3.723,08",
  "liquidado": "R$ 0,00",
  "pago": "R$ 3.723,08",
  "elemento": "PASSAGENS E DESPESAS COM LOCOMOCAO",
  "numero": "204900241 / 2014",
  "data": "20/01/2014",
  "historico": "Fornecimento de passagens aéreas.",
  "itens": [
   {
    "descricao": "CONVERSAO",
    "quantidade": "1.00",
    "valor_unitario": "3.723,08",
    "valor_total": "3.723,08"
   }
  ]
 },
 {
  "instituicao": "PREFEITURA MUNICIPAL DO NATAL",
  "orgao": "SECRETARIA MUNICIPAL DE SAUDE",
  "credor": "12.747.465/0001-90 - HARABELLO PASSAGENS E TURISMO LTDA.",
  "empenhado": "R$ 4.941,54",
  "anulado": "R$ 2.570,28",
  "liquidado": "R$ 2.371,26",
  "pago": "R$ 2.570,28",
  "elemento": "PASSAGENS E DESPESAS COM LOCOMOCAO",
  "numero": "204900239 / 2014",
  "data": "20/01/2014",
  "historico": "Fornecimento de passagens aéreas.",
  "itens": []
 },
 {
  "instituicao": "PREFEITURA MUNICIPAL DO NATAL",
  "orgao": "SECRETARIA MUNICIPAL DE SAUDE",
  "credor": "12.747.465/0001-90 - HARABELLO PASSAGENS E TURISMO LTDA.",
  "empenhado": "R$ 22.564,10",
  "anulado": "R$ 22.564,10",
  "liquidado": "R$ 0,00",
  "pago": "R$ 22.564,10",
  "elemento": "PASSAGENS E DESPESAS COM LOCOMOCAO",
  "numero": "204900237 / 2014",
  "data": "20/01/2014",
  "historico": "Fornecimento de passagens aéreas.",
  "itens": [
   {
    "descricao": "CONVERSAO",
    "quantidade": "1.00",
    "valor_unitario": "22.564,10",
    "valor_total": "22.564,10"
   }
  ]
 },
 {
  "instituicao": "PREFEITURA MUNICIPAL DO NATAL",
  "orgao": "SECRETARIA MUNICIPAL DE SAUDE",
  "credor": "12.747.465/0001-90 - HARABELLO PASSAGENS E TURISMO LTDA.",
  "empenhado": "R$ 15.005,13",
  "anulado": "R$ 10.760,97",
  "liquidado": "R$ 4.244,16",
  "pago": "R$ 10.760,97",
  "elemento": "PASSAGENS E DESPESAS COM LOCOMOCAO",
  "numero": "204900235 / 2014",
  "data": "20/01/2014",
  "historico": "Fornecimento de passagens aéreas.",
  "itens": [
   {
    "descricao": "CONVERSAO",
    "quantidade": "1.00",
    "valor_unitario": "15.005,13",
    "valor_total": "15.005,13"
   }
  ]
 },
 {
  "instituicao": "PREFEITURA MUNICIPAL DO NATAL",
  "orgao": "SECRETARIA MUNICIPAL DE SAUDE",
  "credor": "06.291.731/0001-10 - 3A LOCAÇÕES LTDA - EPP",
  "empenhado": "R$ 110.160,00",
  "anulado": "R$ 72.522,00",
  "liquidado": "R$ 37.638,00",
  "pago": "R$ 72.522,00",
  "elemento": "OUTROS SERVICOS DE TERCEIROS-PESSOA JURIDICA",
  "numero": "204900923 / 2014",
  "data": "07/08/2014",
  "historico": "O presente instrumento tem por objeto a contratação de empresa especializada na prestação de serviço de locação de motocicletas, observando Contrato firmado entre a Secretaria Municipal de Saúde e prestador.",
  "itens": [
   {
    "descricao": "CONVERSAO",
    "quantidade": "1.00",
    "valor_unitario": "110.160,00",
    "valor_total": "110.160,00"
   }
  ]
 },
 {
  "instituicao": "PREFEITURA MUNICIPAL DO NATAL",
  "orgao": "SECRETARIA MUNICIPAL DE SAUDE",
  "credor": "06.291.731/0001-10 - 3A LOCAÇÕES LTDA - EPP",
  "empenhado": "R$ 22.750,00",
  "anulado": "R$ 0,00",
  "liquidado": "R$ 22.750,00",
  "pago": "R$ 0,00",
  "elemento": "OUTROS SERVICOS DE TERCEIROS-PESSOA JURIDICA",
  "numero": "204900626 / 2014",
  "data": "22/05/2014",
  "historico": "O presente instrumento tem por objeto a contratação de empresa especializada na prestação do serviço de transporte de veículos, do tipo ambulância de São Paulo/SP para Natal/RN, conforme Contrato e suas Cláusulas, documento esse firmado e assinado entre as partes.",
  "itens": [
   {
    "descricao": "CONVERSAO",
    "quantidade": "1.00",
    "valor_unitario": "22.750,00",
    "valor_total": "22.750,00"
   }
  ]
 },
 {
  "instituicao": "PREFEITURA MUNICIPAL DO NATAL",
  "orgao": "SECRETARIA MUNICIPAL DE SAUDE",
  "credor": "06.291.731/0001-10 - 3A LOCAÇÕES LTDA - EPP",
  "empenhado": "R$ 119.350,80",
  "anulado": "R$ 0,00",
  "liquidado": "R$ 119.350,80",
  "pago": "R$ 0,00",
  "elemento": "OUTROS SERVICOS DE TERCEIROS-PESSOA JURIDICA",
  "numero": "204900315 / 2014",
  "data": "21/02/2014",
  "historico": "Complementação do empenho nº 252, quanto a locação de veículos.",
  "itens": [
   {
    "descricao": "CONVERSAO",
    "quantidade": "1.00",
    "valor_unitario": "119.350,80",
    "valor_total": "119.350,80"
   }
  ]
 },
 {
  "instituicao": "PREFEITURA MUNICIPAL DO NATAL",
  "orgao": "SECRETARIA MUNICIPAL DE SAUDE",
  "credor": "06.291.731/0001-10 - 3A LOCAÇÕES LTDA - EPP",
  "empenhado": "R$ 119.350,80",
  "anulado": "R$ 0,00",
  "liquidado": "R$ 119.350,80",
  "pago": "R$ 0,00",
  "elemento": "OUTROS SERVICOS DE TERCEIROS-PESSOA JURIDICA",
  "numero": "204900311 / 2014",
  "data": "21/02/2014",
  "historico": "Complementação do empenho nº 253, para a prestação de serviços de locação de veículos.",
  "itens": [
   {
    "descricao": "CONVERSAO",
    "quantidade": "1.00",
    "valor_unitario": "119.350,80",
    "valor_total": "119.350,80"
   }
  ]
 },
 {
  "instituicao": "PREFEITURA MUNICIPAL DO NATAL",
  "orgao": "SECRETARIA MUNICIPAL DE SAUDE",
  "credor": "06.291.731/0001-10 - 3A LOCAÇÕES LTDA - EPP",
  "empenhado": "R$ 3.568,57",
  "anulado": "R$ 0,00",
  "liquidado": "R$ 3.568,57",
  "pago": "R$ 0,00",
  "elemento": "OUTROS SERVICOS DE TERCEIROS-PESSOA JURIDICA",
  "numero": "204900307 / 2014",
  "data": "21/02/2014",
  "historico": "Prestação de serviços de locação de veículos.",
  "itens": [
   {
    "descricao": "CONVERSAO",
    "quantidade": "1.00",
    "valor_unitario": "3.568,57",
    "valor_total": "3.568,57"
   }
  ]
 },
 {
  "instituicao": "PREFEITURA MUNICIPAL DO NATAL",
  "orgao": "SECRETARIA MUNICIPAL DE SAUDE",
  "credor": "06.291.731/0001-10 - 3A LOCAÇÕES LTDA - EPP",
  "empenhado": "R$ 171.859,68",
  "anulado": "R$ 0,00",
  "liquidado": "R$ 171.859,68",
  "pago": "R$ 0,00",
  "elemento": "OUTROS SERVICOS DE TERCEIROS-PESSOA JURIDICA",
  "numero": "204900305 / 2014",
  "data": "21/02/2014",
  "historico": "Complementação do empenho nº256, na prestação de serviços de locação de veículos.",
  "itens": [
   {
    "descricao": "CONVERSAO",
    "quantidade": "1.00",
    "valor_unitario": "171.859,68",
    "valor_total": "171.859,68"
   }
  ]
 },
 {
  "instituicao": "PREFEITURA MUNICIPAL DO NATAL",
  "orgao": "SECRETARIA MUNICIPAL DE SAUDE",
  "credor": "06.291.731/0001-10 - 3A LOCAÇÕES LTDA - EPP",
  "empenhado": "R$ 78.567,20",
  "anulado": "R$ 0,00",
  "liquidado": "R$ 78.567,15",
  "pago": "R$ 0,00",
  "elemento": "OUTROS SERVICOS DE TERCEIROS-PESSOA JURIDICA",
  "numero": "204900304 / 2014",
  "data": "21/02/2014",
  "historico": "Complementação do empenho nº 255, na prestação de serviços de locação de veículos.",
  "itens": [
   {
    "descricao": "CONVERSAO",
    "quantidade": "1.00",
    "valor_unitario": "78.567,20",
    "valor_total": "78.567,20"
   }
  ]
 },
 {
  "instituicao": "PREFEITURA MUNICIPAL DO NATAL",
  "orgao": "SECRETARIA MUNICIPAL DE SAUDE",
  "credor": "06.291.731/0001-10 - 3A LOCAÇÕES LTDA - EPP",
  "empenhado": "R$ 5.097,95",
  "anulado": "R$ 0,00",
  "liquidado": "R$ 5.097,95",
  "pago": "R$ 0,00",
  "elemento": "OUTROS SERVICOS DE TERCEIROS-PESSOA JURIDICA",
  "numero": "204900303 / 2014",
  "data": "21/02/2014",
  "historico": "Prestação de serviços de locação de veículos, conforme contrato firmado.",
  "itens": [
   {
    "descricao": "CONVERSAO",
    "quantidade": "1.00",
    "valor_unitario": "5.097,95",
    "valor_total": "5.097,95"
   }
  ]
 },
 {
  "instituicao": "PREFEITURA MUNICIPAL DO NATAL",
  "orgao": "SECRETARIA MUNICIPAL DE SAUDE",
  "credor": "06.291.731/0001-10 - 3A LOCAÇÕES LTDA - EPP",
  "empenhado": "R$ 3.000,00",
  "anulado": "R$ 0,00",
  "liquidado": "R$ 3.000,00",
  "pago": "R$ 0,00",
  "elemento": "OUTROS SERVICOS DE TERCEIROS-PESSOA JURIDICA",
  "numero": "204900256 / 2014",
  "data": "31/01/2014",
  "historico": "O presente instrumento tem por objeto o serviço de contratação de empresa especializada na prestação de serviços de locação de veiculos, fazendo referencia ao iten 11, observando contrato firmado.",
  "itens": [
   {
    "descricao": "CONVERSAO",
    "quantidade": "1.00",
    "valor_unitario": "3.000,00",
    "valor_total": "3.000,00"
   }
  ]
 },
 {
  "instituicao": "PREFEITURA MUNICIPAL DO NATAL",
  "orgao": "SECRETARIA MUNICIPAL DE SAUDE",
  "credor": "06.291.731/0001-10 - 3A LOCAÇÕES LTDA - EPP",
  "empenhado": "R$ 3.000,00",
  "anulado": "R$ 0,00",
  "liquidado": "R$ 3.000,00",
  "pago": "R$ 0,00",
  "elemento": "OUTROS SERVICOS DE TERCEIROS-PESSOA JURIDICA",
  "numero": "204900255 / 2014",
  "data": "31/01/2014",
  "historico": "O presente instrumento tem por objeto o serviço de contratação de empresa especializada na prestação de serviços de locação de veiculos, fazendo referencia ao iten 11, observando contrato firmado.",
  "itens": [
   {
    "descricao": "CONVERSAO",
    "quantidade": "1.00",
    "valor_unitario": "3.000,00",
    "valor_total": "3.000,00"
   }
  ]
 },
 {
  "instituicao": "PREFEITURA MUNICIPAL DO NATAL",
  "orgao": "SECRETARIA MUNICIPAL DE SAUDE",
  "credor": "09.090.275/0001-38 - A AZEVEDO HOTÉIS E TURISMO LTDA.",
  "empenhado": "R$ 2.562,66",
  "anulado": "R$ 0,00",
  "liquidado": "R$ 2.562,66",
  "pago": "R$ 0,00",
  "elemento": "OUTROS SERVICOS DE TERCEIROS-PESSOA JURIDICA",
  "numero": "204901571 / 2014",
  "data": "22/12/2014",
  "historico": "Complementação do empenho nº 294.",
  "itens": [
   {
    "descricao": "CONVERSAO",
    "quantidade": "1.00",
    "valor_unitario": "2.562,66",
    "valor_total": "2.562,66"
   }
  ]
 },
 {
  "instituicao": "PREFEITURA MUNICIPAL DO NATAL",
  "orgao": "SECRETARIA MUNICIPAL DE SAUDE",
  "credor": "09.090.275/0001-38 - A AZEVEDO HOTÉIS E TURISMO LTDA.",
  "empenhado": "R$ 41,34",
  "anulado": "R$ 0,00",
  "liquidado": "R$ 41,34",
  "pago": "R$ 0,00",
  "elemento": "OUTROS SERVICOS DE TERCEIROS-PESSOA JURIDICA",
  "numero": "204901570 / 2014",
  "data": "22/12/2014",
  "historico": "Complementação do empenho nº 297.",
  "itens": [
   {
    "descricao": "CONVERSAO",
    "quantidade": "1.00",
    "valor_unitario": "41,34",
    "valor_total": "41,34"
   }
  ]
 },
 {
  "instituicao": "PREFEITURA MUNICIPAL DO NATAL",
  "orgao": "SECRETARIA MUNICIPAL DE SAUDE",
  "credor": "09.090.275/0001-38 - A AZEVEDO HOTÉIS E TURISMO LTDA.",
  "empenhado": "R$ 124,00",
  "anulado": "R$ 0,00",
  "liquidado": "R$ 124,00",
  "pago": "R$ 0,00",
  "elemento": "OUTROS SERVICOS DE TERCEIROS-PESSOA JURIDICA",
  "numero": "204901569 / 2014",
  "data": "22/12/2014",
  "historico": "Complementação do empenho nº 296.",
  "itens": [
   {
    "descricao": "CONVERSAO",
    "quantidade": "1.00",
    "valor_unitario": "124,00",
    "valor_total": "124,00"
   }
  ]
 },
 {
  "instituicao": "PREFEITURA MUNICIPAL DO NATAL",
  "orgao": "SECRETARIA MUNICIPAL DE SAUDE",
  "credor": "09.090.275/0001-38 - A AZEVEDO HOTÉIS E TURISMO LTDA.",
  "empenhado": "R$ 620,00",
  "anulado": "R$ 0,00",
  "liquidado": "R$ 620,00",
  "pago": "R$ 0,00",
  "elemento": "OUTROS SERVICOS DE TERCEIROS-PESSOA JURIDICA",
  "numero": "204901568 / 2014",
  "data": "22/12/2014",
  "historico": "Complementação do empenho nº 295.",
  "itens": [
   {
    "descricao": "CONVERSAO",
    "quantidade": "1.00",
    "valor_unitario": "620,00",
    "valor_total": "620,00"
   }
  ]
 },
 {
  "instituicao": "PREFEITURA MUNICIPAL DO NATAL",
  "orgao": "SECRETARIA MUNICIPAL DE SAUDE",
  "credor": "09.090.275/0001-38 - A AZEVEDO HOTÉIS E TURISMO LTDA.",
  "empenhado": "R$ 785,33",
  "anulado": "R$ 0,00",
  "liquidado": "R$ 785,33",
  "pago": "R$ 0,00",
  "elemento": "OUTROS SERVICOS DE TERCEIROS-PESSOA JURIDICA",
  "numero": "204901567 / 2014",
  "data": "22/12/2014",
  "historico": "Complementação do empenho nº 293.",
  "itens": [
   {
    "descricao": "CONVERSAO",
    "quantidade": "1.00",
    "valor_unitario": "785,33",
    "valor_total": "785,33"
   }
  ]
 },
 {
  "instituicao": "PREFEITURA MUNICIPAL DO NATAL",
  "orgao": "SECRETARIA MUNICIPAL DE SAUDE",
  "credor": "09.090.275/0001-38 - A AZEVEDO HOTÉIS E TURISMO LTDA.",
  "empenhado": "R$ 8.964,78",
  "anulado": "R$ 0,00",
  "liquidado": "R$ 8.964,78",
  "pago": "R$ 0,00",
  "elemento": "OUTROS SERVICOS DE TERCEIROS-PESSOA JURIDICA",
  "numero": "204900297 / 2014",
  "data": "19/02/2014",
  "historico": "Locação do imóvel, situado à Rua Fabrício Pedroza, nº 915, Ala Sul, Bairro - Petropolis, Natal, para funcionamento da SMS.",
  "itens": [
   {
    "descricao": "CONVERSAO",
    "quantidade": "1.00",
    "valor_unitario": "8.964,78",
    "valor_total": "8.964,78"
   }
  ]
 },
 {
  "instituicao": "PREFEITURA MUNICIPAL DO NATAL",
  "orgao": "SECRETARIA MUNICIPAL DE SAUDE",
  "credor": "09.090.275/0001-38 - A AZEVEDO HOTÉIS E TURISMO LTDA.",
  "empenhado": "R$ 17.929,78",
  "anulado": "R$ 0,00",
  "liquidado": "R$ 17.929,78",
  "pago": "R$ 0,00",
  "elemento": "OUTROS SERVICOS DE TERCEIROS-PESSOA JURIDICA",
  "numero": "204900296 / 2014",
  "data": "19/02/2014",
  "historico": "Locação do imóvel, situado à Rua Fabrício Pedroza, nº 915, Ala Sul, Bairro - Petropolis, Natal, para funcionamento da SMS.",
  "itens": [
   {
    "descricao": "CONVERSAO",
    "quantidade": "1.00",
    "valor_unitario": "17.929,78",
    "valor_total": "17.929,78"
   }
  ]
 },
 {
  "instituicao": "PREFEITURA MUNICIPAL DO NATAL",
  "orgao": "SECRETARIA MUNICIPAL DE SAUDE",
  "credor": "09.090.275/0001-38 - A AZEVEDO HOTÉIS E TURISMO LTDA.",
  "empenhado": "R$ 98.613,55",
  "anulado": "R$ 0,00",
  "liquidado": "R$ 98.613,55",
  "pago": "R$ 0,00",
  "elemento": "OUTROS SERVICOS DE TERCEIROS-PESSOA JURIDICA",
  "numero": "204900295 / 2014",
  "data": "19/02/2014",
  "historico": "Locação do imóvel, situado à Rua Fabrício Pedroza, nº 915, Ala Sul, Bairro - Petropolis, Natal, para funcionamento da SMS.",
  "itens": [
   {
    "descricao": "CONVERSAO",
    "quantidade": "1.00",
    "valor_unitario": "98.613,55",
    "valor_total": "98.613,55"
   }
  ]
 },
 {
  "instituicao": "PREFEITURA MUNICIPAL DO NATAL",
  "orgao": "SECRETARIA MUNICIPAL DE SAUDE",
  "credor": "09.090.275/0001-38 - A AZEVEDO HOTÉIS E TURISMO LTDA.",
  "empenhado": "R$ 412.383,78",
  "anulado": "R$ 0,00",
  "liquidado": "R$ 412.383,78",
  "pago": "R$ 0,00",
  "elemento": "OUTROS SERVICOS DE TERCEIROS-PESSOA JURIDICA",
  "numero": "204900294 / 2014",
  "data": "19/02/2014",
  "historico": "Locação do imóvel, situado à Rua Fabrício Pedroza, nº 915, Ala Sul, Bairro - Petropolis, Natal, para funcionamento da SMS.",
  "itens": [
   {
    "descricao": "CONVERSAO",
    "quantidade": "1.00",
    "valor_unitario": "412.383,78",
    "valor_total": "412.383,78"
   }
  ]
 },
 {
  "instituicao": "PREFEITURA MUNICIPAL DO NATAL",
  "orgao": "SECRETARIA MUNICIPAL DE SAUDE",
  "credor": "09.090.275/0001-38 - A AZEVEDO HOTÉIS E TURISMO LTDA.",
  "empenhado": "R$ 125.508,11",
  "anulado": "R$ 0,00",
  "liquidado": "R$ 125.508,11",
  "pago": "R$ 0,00",
  "elemento": "OUTROS SERVICOS DE TERCEIROS-PESSOA JURIDICA",
  "numero": "204900293 / 2014",
  "data": "19/02/2014",
  "historico": "Locação do imóvel, situado à Rua Fabrício Pedroza, nº 915, Ala Sul, Bairro - Petrópolis, Natal, para funcionamento da SMS.",
  "itens": [
   {
    "descricao": "CONVERSAO",
    "quantidade": "1.00",
    "valor_unitario": "125.508,11",
    "valor_total": "125.508,11"
   }
  ]
 },
 {
  "instituicao": "PREFEITURA MUNICIPAL DO NATAL",
  "orgao": "SECRETARIA MUNICIPAL DE SAUDE",
  "credor": "00.331.788/0024-05 - AIR LIQUIDE BRASIL LTDA",
  "empenhado": "R$ 109.056,42",
  "anulado": "R$ 0,00",
  "liquidado": "R$ 0,00",
  "pago": "R$ 0,00",
  "elemento": "OUTROS SERVICOS DE TERCEIROS-PESSOA JURIDICA",
  "numero": "204901255 / 2014",
  "data": "21/10/2014",
  "historico": "O presente instrumento tem por objeto a prestação de serviços de instalação, montagem e locação de sistemas de ar comprimido medicinal, conforme contrato firmado.",
  "itens": [
   {
    "descricao": "CONVERSAO",
    "quantidade": "1.00",
    "valor_unitario": "109.056,42",
    "valor_total": "109.056,42"
   }
  ]
 },
 {
  "instituicao": "PREFEITURA MUNICIPAL DO NATAL",
  "orgao": "SECRETARIA MUNICIPAL DE SAUDE",
  "credor": "00.331.788/0024-05 - AIR LIQUIDE BRASIL LTDA",
  "empenhado": "R$ 69.375,00",
  "anulado": "R$ 0,00",
  "liquidado": "R$ 22.500,00",
  "pago": "R$ 0,00",
  "elemento": "OUTROS SERVICOS DE TERCEIROS-PESSOA JURIDICA",
  "numero": "204900915 / 2014",
  "data": "07/08/2014",
  "historico": "O presente instrumento tem por objeto a prestação de serviços de instalação, montagem e locação de sistemas de ar comprimido medicinal, conforme 2º Termo Aditivo firmado.",
  "itens": [
   {
    "descricao": "CONVERSAO",
    "quantidade": "1.00",
    "valor_unitario": "69.375,00",
    "valor_total": "69.375,00"
   }
  ]
 },
 {
  "instituicao": "PREFEITURA MUNICIPAL DO NATAL",
  "orgao": "SECRETARIA MUNICIPAL DE SAUDE",
  "credor": "00.331.788/0024-05 - AIR LIQUIDE BRASIL LTDA",
  "empenhado": "R$ 226.922,50",
  "anulado": "R$ 185.297,50",
  "liquidado": "R$ 41.625,00",
  "pago": "R$ 185.297,50",
  "elemento": "OUTROS SERVICOS DE TERCEIROS-PESSOA JURIDICA",
  "numero": "204900289 / 2014",
  "data": "18/02/2014",
  "historico": "O presente instrumento tem por objeto a prorrogação do Contrato 009/2013 por mais 06 (seis) meses, referente a contratação de empresa especializada para prestação de serviços de instalação, montagem e locação de sistema de ar comprimido medicinal, observando a Cláusula primeiro do referido Termo Aditivo.",
  "itens": [
   {
    "descricao": "CONVERSAO",
    "quantidade": "1.00",
    "valor_unitario": "226.922,50",
    "valor_total": "226.922,50"
   }
  ]
 },
 {
  "instituicao": "PREFEITURA MUNICIPAL DO NATAL",
  "orgao": "SECRETARIA MUNICIPAL DE SAUDE",
  "credor": "00.331.788/0024-05 - AIR LIQUIDE BRASIL LTDA",
  "empenhado": "R$ 13.875,00",
  "anulado": "R$ 0,00",
  "liquidado": "R$ 13.875,00",
  "pago": "R$ 0,00",
  "elemento": "OUTROS SERVICOS DE TERCEIROS-PESSOA JURIDICA",
  "numero": "204900096 / 2014",
  "data": "20/01/2014",
  "historico": "Locação de sistemas de ar medicinal conforme autos.",
  "itens": [
   {
    "descricao": "CONVERSAO",
    "quantidade": "1.00",
    "valor_unitario": "13.875,00",
    "valor_total": "13.875,00"
   }
  ]
 },
 {
  "instituicao": "PREFEITURA MUNICIPAL DO NATAL",
  "orgao": "SECRETARIA MUNICIPAL DE SAUDE",
  "credor": "02.871.166/0001-09 - AJS COMÉRCIO E REPRESENTAÇÕES LTDA.-ME",
  "empenhado": "R$ 70.980,00",
  "anulado": "R$ 70.980,00",
  "liquidado": "R$ 0,00",
  "pago": "R$ 70.980,00",
  "elemento": "OUTROS SERVICOS DE TERCEIROS-PESSOA JURIDICA",
  "numero": "204900388 / 2014",
  "data": "28/02/2014",
  "historico": "O presente instrumento tem por objeto a contratação de empresa especializada no serviço de confecção de camisetas, conforme especificações e quantitativos informados na Ordem de Serviço e, nos termos contratados observando a Cláusula nona do Contrato informado. Observação; A despesa no valor informado foi empenhada na fonte 111, por falta de orçamento na fonte original do Contrato firmado, ou seja a fonte 183.",
  "itens": [
   {
    "descricao": "CONVERSAO",
    "quantidade": "1.00",
    "valor_unitario": "70.980,00",
    "valor_total": "70.980,00"
   }
  ]
 },
 {
  "instituicao": "PREFEITURA MUNICIPAL DO NATAL",
  "orgao": "SECRETARIA MUNICIPAL DE SAUDE",
  "credor": "02.871.166/0001-09 - AJS COMÉRCIO E REPRESENTAÇÕES LTDA.-ME",
  "empenhado": "R$ 153.790,00",
  "anulado": "R$ 153.790,00",
  "liquidado": "R$ 0,00",
  "pago": "R$ 153.790,00",
  "elemento": "OUTROS SERVICOS DE TERCEIROS-PESSOA JURIDICA",
  "numero": "204900387 / 2014",
  "data": "28/02/2014",
  "historico": "O presente instrumento tem por objeto a contratação de empresa especializada no serviço de confecção de camisetas, conforme especificações e quantitativos informados na Ordem de Serviço e, nos termos contratados observando a Cláusula nona do Contrato informado.",
  "itens": [
   {
    "descricao": "CONVERSAO",
    "quantidade": "1.00",
    "valor_unitario": "153.790,00",
    "valor_total": "153.790,00"
   }
  ]
 },
 {
  "instituicao": "PREFEITURA MUNICIPAL DO NATAL",
  "orgao": "SECRETARIA MUNICIPAL DE SAUDE",
  "credor": "02.871.166/0001-09 - AJS COMÉRCIO E REPRESENTAÇÕES LTDA.-ME",
  "empenhado": "R$ 5.915,00",
  "anulado": "R$ 5.915,00",
  "liquidado": "R$ 0,00",
  "pago": "R$ 5.915,00",
  "elemento": "OUTROS SERVICOS DE TERCEIROS-PESSOA JURIDICA",
  "numero": "204900386 / 2014",
  "data": "28/02/2014",
  "historico": "O presente instrumento tem por objeto a contratação de empresa especializada no serviço de confecção de camisetas, conforme especificações e quantitativos informados na Ordem de Serviço e, nos termos contratados observando a Cláusula nona do Contrato informado.",
  "itens": [
   {
    "descricao": "CONVERSAO",
    "quantidade": "1.00",
    "valor_unitario": "5.915,00",
    "valor_total": "5.915,00"
   }
  ]
 },
 {
  "instituicao": "PREFEITURA MUNICIPAL DO NATAL",
  "orgao": "SECRETARIA MUNICIPAL DE SAUDE",
  "credor": "03.527.573/0001-66 - ANDRE NAVARRO MESQUITA",
  "empenhado": "R$ 6.050,58",
  "anulado": "R$ 35,06",
  "liquidado": "R$ 6.015,52",
  "pago": "R$ 35,06",
  "elemento": "OUTROS SERVICOS DE TERCEIROS-PESSOA JURIDICA",
  "numero": "204900533 / 2014",
  "data": "09/04/2014",
  "historico": "Serviço de manutenção preventiva e corretiva com substituição de peças e acessórios originais dos fabricantes, sem uso prévio e assistência mecânica, elétrica, reboque, lanternagem e pintura em geral dos veículos da SMS, referente ao exercício 2014, conforme 1º Termo Aditivo ao Contrato firmado.",
  "itens": [
   {
    "descricao": "CONVERSAO",
    "quantidade": "1.00",
    "valor_unitario": "6.050,58",
    "valor_total": "6.050,58"
   }
  ]
 },
 {
  "instituicao": "PREFEITURA MUNICIPAL DO NATAL",
  "orgao": "SECRETARIA MUNICIPAL DE SAUDE",
  "credor": "03.527.573/0001-66 - ANDRE NAVARRO MESQUITA",
  "empenhado": "R$ 5.975,96",
  "anulado": "R$ 0,00",
  "liquidado": "R$ 5.975,96",
  "pago": "R$ 0,00",
  "elemento": "OUTROS SERVICOS DE TERCEIROS-PESSOA JURIDICA",
  "numero": "204900531 / 2014",
  "data": "09/04/2014",
  "historico": "Serviço de manutenção preventiva e corretiva com substituição de peças e acessórios originais dos fabricantes, sem uso prévio e assistência mecânica, elétrica, reboque, lanternagem e pintura em geral dos veículos da SMS, referente ao exercício 2014, conforme 1º Termo Aditivo ao Contrato firmado.",
  "itens": [
   {
    "descricao": "CONVERSAO",
    "quantidade": "1.00",
    "valor_unitario": "5.975,96",
    "valor_total": "5.975,96"
   }
  ]
 },
 {
  "instituicao": "PREFEITURA MUNICIPAL DO NATAL",
  "orgao": "SECRETARIA MUNICIPAL DE SAUDE",
  "credor": "03.527.573/0001-66 - ANDRE NAVARRO MESQUITA",
  "empenhado": "R$ 32.608,11",
  "anulado": "R$ 67,98",
  "liquidado": "R$ 32.540,13",
  "pago": "R$ 67,98",
  "elemento": "OUTROS SERVICOS DE TERCEIROS-PESSOA JURIDICA",
  "numero": "204900528 / 2014",
  "data": "09/04/2014",
  "historico": "Serviço de manutenção preventiva e corretiva com substituição de peças e acessórios originais dos fabricantes, sem uso prévio e assistência mecânica, elétrica, reboque, lanternagem e pintura em geral dos veículos da SMS, referente ao exercício 2014, conforme 1º Termo Aditivo ao Contrato firmado.",
  "itens": [
   {
    "descricao": "CONVERSAO",
    "quantidade": "1.00",
    "valor_unitario": "32.608,11",
    "valor_total": "32.608,11"
   }
  ]
 },
 {
  "instituicao": "PREFEITURA MUNICIPAL DO NATAL",
  "orgao": "SECRETARIA MUNICIPAL DE SAUDE",
  "credor": "03.527.573/0001-66 - ANDRE NAVARRO MESQUITA",
  "empenhado": "R$ 15.247,35",
  "anulado": "R$ 0,00",
  "liquidado": "R$ 15.247,35",
  "pago": "R$ 0,00",
  "elemento": "OUTROS SERVICOS DE TERCEIROS-PESSOA JURIDICA",
  "numero": "204900131 / 2014",
  "data": "20/01/2014",
  "historico": "Serviço de Manutenção preventiva e corretiva com substituição de peças e acessórios originais dos fabricantes, sem uso prévio e assistência mecânica, elétrica reboque, lanternagem e pintura em geral dos veículos oficiais da SMS, referente a 03(três) meses e 03(dias) do atual exercício.",
  "itens": [
   {
    "descricao": "CONVERSAO",
    "quantidade": "1.00",
    "valor_unitario": "15.247,35",
    "valor_total": "15.247,35"
   }
  ]
 },
 {
  "instituicao": "PREFEITURA MUNICIPAL DO NATAL",
  "orgao": "SECRETARIA MUNICIPAL DE SAUDE",
  "credor": "03.527.573/0001-66 - ANDRE NAVARRO MESQUITA",
  "empenhado": "R$ 1.449,42",
  "anulado": "R$ 11,65",
  "liquidado": "R$ 1.437,77",
  "pago": "R$ 11,65",
  "elemento": "OUTROS SERVICOS DE TERCEIROS-PESSOA JURIDICA",
  "numero": "204900130 / 2014",
  "data": "20/01/2014",
  "historico": "Serviço de Manutenção preventiva e corretiva com substituição de peças e acessórios originais dos fabricantes, sem uso prévio e assistência mecânica, elétrica reboque, lanternagem e pintura em geral dos veículos oficiais da SMS, referente a 03(três) meses e 03(dias) do atual exercício.",
  "itens": [
   {
    "descricao": "CONVERSAO",
    "quantidade": "1.00",
    "valor_unitario": "1.449,42",
    "valor_total": "1.449,42"
   }
  ]
 },
 {
  "instituicao": "PREFEITURA MUNICIPAL DO NATAL",
  "orgao": "SECRETARIA MUNICIPAL DE SAUDE",
  "credor": "03.527.573/0001-66 - ANDRE NAVARRO MESQUITA",
  "empenhado": "R$ 1.524,04",
  "anulado": "R$ 0,06",
  "liquidado": "R$ 1.523,98",
  "pago": "R$ 0,06",
  "elemento": "OUTROS SERVICOS DE TERCEIROS-PESSOA JURIDICA",
  "numero": "204900126 / 2014",
  "data": "20/01/2014",
  "historico": "Serviço de Manutenção preventiva e corretiva com substituição de peças e acessórios originais dos fabricantes, sem uso prévio e assistência mecânica, elétrica reboque, lanternagem e pintura em geral dos veículos oficiais da SMS, referente a 03(três) meses e 03(dias) do atual exercício.",
  "itens": [
   {
    "descricao": "CONVERSAO",
    "quantidade": "1.00",
    "valor_unitario": "1.524,04",
    "valor_total": "1.524,04"
   }
  ]
 },
 {
  "instituicao": "PREFEITURA MUNICIPAL DO NATAL",
  "orgao": "SECRETARIA MUNICIPAL DE SAUDE",
  "credor": "08.453.920/0001-77 - ASSOC.DE PAIS E AMIGOS DOS EXCEPCIONAIS",
  "empenhado": "R$ 13.177,20",
  "anulado": "R$ 0,00",
  "liquidado": "R$ 7.522,25",
  "pago": "R$ 0,00",
  "elemento": "OUTROS SERVICOS DE TERCEIROS-PESSOA JURIDICA",
  "numero": "204901011 / 2014",
  "data": "29/08/2014",
  "historico": "Serviços Ambulatoriais especializados na área de Fisioterapia, a serem prestados aos Usuários do Sistema Único de Saúde - SUS, em conformidade com o Contrato de n.º 169/2014, autorizado pelo Titular da Pasta da SMS nos autos do Processo de n.º 005830/2014-49.",
  "itens": [
   {
    "descricao": "CONVERSAO",
    "quantidade": "1.00",
    "valor_unitario": "13.177,20",
    "valor_total": "13.177,20"
   }
  ]
 },
 {
  "instituicao": "PREFEITURA MUNICIPAL DO NATAL",
  "orgao": "SECRETARIA MUNICIPAL DE SAUDE",
  "credor": "08.453.920/0001-77 - ASSOC.DE PAIS E AMIGOS DOS EXCEPCIONAIS",
  "empenhado": "R$ 52.708,80",
  "anulado": "R$ 0,00",
  "liquidado": "R$ 52.708,80",
  "pago": "R$ 0,00",
  "elemento": "OUTROS SERVICOS DE TERCEIROS-PESSOA JURIDICA",
  "numero": "204900034 / 2014",
  "data": "20/01/2014",
  "historico": "Referente a prestação de serviços aos usuarios do SUS na area de fisioterapia.",
  "itens": [
   {
    "descricao": "CONVERSAO",
    "quantidade": "1.00",
    "valor_unitario": "52.708,80",
    "valor_total": "52.708,80"
   }
  ]
 },
 {
  "instituicao": "PREFEITURA MUNICIPAL DO NATAL",
  "orgao": "SECRETARIA MUNICIPAL DE SAUDE",
  "credor": "08.679.011/0001-51 - ASSOCIACAO DE ORIENT. DEFICIENTES",
  "empenhado": "R$ 613,01",
  "anulado": "R$ 0,00",
  "liquidado": "R$ 0,00",
  "pago": "R$ 0,00",
  "elemento": "OUTROS SERVICOS DE TERCEIROS-PESSOA JURIDICA",
  "numero": "204901603 / 2014",
  "data": "29/12/2014",
  "historico": "O presente instrumento tem por objeto a prorrogação do contrato original, no que tange aos serviços especializados na área de odontologia e fisioterapia, conforme 3º Termo Aditivo.",
  "itens": [
   {
    "descricao": "CONVERSAO",
    "quantidade": "1.00",
    "valor_unitario": "613,01",
    "valor_total": "613,01"
   }
  ]
 },
 {
  "instituicao": "PREFEITURA MUNICIPAL DO NATAL",
  "orgao": "SECRETARIA MUNICIPAL DE SAUDE",
  "credor": "08.679.011/0001-51 - ASSOCIACAO DE ORIENT. DEFICIENTES",
  "empenhado": "R$ 72.415,37",
  "anulado": "R$ 0,00",
  "liquidado": "R$ 0,00",
  "pago": "R$ 0,00",
  "elemento": "OUTROS SERVICOS DE TERCEIROS-PESSOA JURIDICA",
  "numero": "204901602 / 2014",
  "data": "29/12/2014",
  "historico": "O presente instrumento tem por objeto a prorrogação do contrato original, no que tange aos serviços especializados na área de odontologia e fisioterapia, conforme 3º Termo Aditivo.",
  "itens": [
   {
    "descricao": "CONVERSAO",
    "quantidade": "1.00",
    "valor_unitario": "72.415,37",
    "valor_total": "72.415,37"
   }
  ]
 },
 {
  "instituicao": "PREFEITURA MUNICIPAL DO NATAL",
  "orgao": "SECRETARIA MUNICIPAL DE SAUDE",
  "credor": "08.679.011/0001-51 - ASSOCIACAO DE ORIENT. DEFICIENTES",
  "empenhado": "R$ 1.381.579,68",
  "anulado": "R$ 180.000,00",
  "liquidado": "R$ 959.095,63",
  "pago": "R$ 180.000,00",
  "elemento": "OUTROS SERVICOS DE TERCEIROS-PESSOA JURIDICA",
  "numero": "204900035 / 2014",
  "data": "20/01/2014",
  "historico": "Referente a prestação de serviços aos usuarios do SUS na area de odontologia e fisioterapia.",
  "itens": [
   {
    "descricao": "CONVERSAO",
    "quantidade": "1.00",
    "valor_unitario": "1.381.579,68",
    "valor_total": "1.381.579,68"
   }
  ]
 },
 {
  "instituicao": "PREFEITURA MUNICIPAL DO NATAL",
  "orgao": "SECRETARIA MUNICIPAL DE SAUDE",
  "credor": "06.281.627/0001-44 - CAW DISTRIBUIDORA DE PEÇAS LTDA",
  "empenhado": "R$ 24.003,72",
  "anulado": "R$ 0,00",
  "liquidado": "R$ 20.225,33",
  "pago": "R$ 0,00",
  "elemento": "OUTROS SERVICOS DE TERCEIROS-PESSOA JURIDICA",
  "numero": "204900595 / 2014",
  "data": "07/05/2014",
  "historico": "Serviço de manutenção preventiva e corretiva com substituição de peças e acessórios originais, referente 08 meses e 27 dias do exercício 2014.",
  "itens": [
   {
    "descricao": "CONVERSAO",
    "quantidade": "1.00",
    "valor_unitario": "24.003,72",
    "valor_total": "24.003,72"
   }
  ]
 },
 {
  "instituicao": "PREFEITURA MUNICIPAL DO NATAL",
  "orgao": "SECRETARIA MUNICIPAL DE SAUDE",
  "credor": "06.281.627/0001-44 - CAW DISTRIBUIDORA DE PEÇAS LTDA",
  "empenhado": "R$ 33.304,27",
  "anulado": "R$ 0,00",
  "liquidado": "R$ 13.958,30",
  "pago": "R$ 0,00",
  "elemento": "OUTROS SERVICOS DE TERCEIROS-PESSOA JURIDICA",
  "numero": "204900593 / 2014",
  "data": "07/05/2014",
  "historico": "Serviço de manutenção preventiva e corretiva com substituição de peças e acessórios originais, referente 08 meses e 27 dias do exercício 2014.",
  "itens": [
   {
    "descricao": "CONVERSAO",
    "quantidade": "1.00",
    "valor_unitario": "33.304,27",
    "valor_total": "33.304,27"
   }
  ]
 },
 {
  "instituicao": "PREFEITURA MUNICIPAL DO NATAL",
  "orgao": "SECRETARIA MUNICIPAL DE SAUDE",
  "credor": "06.281.627/0001-44 - CAW DISTRIBUIDORA DE PEÇAS LTDA",
  "empenhado": "R$ 13.991,33",
  "anulado": "R$ 0,00",
  "liquidado": "R$ 13.991,33",
  "pago": "R$ 0,00",
  "elemento": "OUTROS SERVICOS DE TERCEIROS-PESSOA JURIDICA",
  "numero": "204900153 / 2014",
  "data": "20/01/2014",
  "historico": "Serviço de manutenção preventiva e corretiva com substituição de peças e acessórios originais dos fabricantes, sem uso prévio e assistência mecânica, elétrica, reboque, lanternagem e pintura em geral dos veículos oficiais da SMS, conforme contrato 38/2013 firmado. Referente ao pagamento de 03(três) meses e 03(três) dias do exercício 2014.",
  "itens": [
   {
    "descricao": "CONVERSAO",
    "quantidade": "1.00",
    "valor_unitario": "13.991,33",
    "valor_total": "13.991,33"
   }
  ]
 },
 {
  "instituicao": "PREFEITURA MUNICIPAL DO NATAL",
  "orgao": "SECRETARIA MUNICIPAL DE SAUDE",
  "credor": "06.281.627/0001-44 - CAW DISTRIBUIDORA DE PEÇAS LTDA",
  "empenhado": "R$ 5.996,28",
  "anulado": "R$ 0,00",
  "liquidado": "R$ 5.860,60",
  "pago": "R$ 0,00",
  "elemento": "OUTROS SERVICOS DE TERCEIROS-PESSOA JURIDICA",
  "numero": "204900152 / 2014",
  "data": "20/01/2014",
  "historico": "Serviço de manutenção preventiva e corretiva com substituição de peças e acessórios originais dos fabricantes, sem uso prévio e assistência mecânica, elétrica, reboque, lanternagem e pintura em geral dos veículos oficiais da SMS, conforme contrato 38/2013 firmado. Referente ao pagamento de 03(três) meses e 03(três) dias do exercício 2014.",
  "itens": [
   {
    "descricao": "CONVERSAO",
    "quantidade": "1.00",
    "valor_unitario": "5.996,28",
    "valor_total": "5.996,28"
   }
  ]
 },
 {
  "instituicao": "PREFEITURA MUNICIPAL DO NATAL",
  "orgao": "SECRETARIA MUNICIPAL DE SAUDE",
  "credor": "01.502.746/0001-66 - CENTRO AVANÇADO DE OFTAMOLOGIA DO RIO GR",
  "empenhado": "R$ 134.687,20",
  "anulado": "R$ 72.736,91",
  "liquidado": "R$ 29.950,29",
  "pago": "R$ 72.736,91",
  "elemento": "OUTROS SERVICOS DE TERCEIROS-PESSOA JURIDICA",
  "numero": "204901379 / 2014",
  "data": "18/11/2014",
  "historico": "O presente tem por objeto a prestação de serviços ambulatoriais especializados na área de Oftalmologia, a serem prestados aos Usuários do SUS/Natal, conforme Contrato firmado entre as partes.",
  "itens": [
   {
    "descricao": "CONVERSAO",
    "quantidade": "1.00",
    "valor_unitario": "134.687,20",
    "valor_total": "134.687,20"
   }
  ]
 },
 {
  "instituicao": "PREFEITURA MUNICIPAL DO NATAL",
  "orgao": "SECRETARIA MUNICIPAL DE SAUDE",
  "credor": "01.502.746/0001-66 - CENTRO AVANÇADO DE OFTAMOLOGIA DO RIO GR",
  "empenhado": "R$ 607.172,40",
  "anulado": "R$ 471.995,27",
  "liquidado": "R$ 135.177,13",
  "pago": "R$ 471.995,27",
  "elemento": "OUTROS SERVICOS DE TERCEIROS-PESSOA JURIDICA",
  "numero": "204900002 / 2014",
  "data": "20/01/2014",
  "historico": "Referente a prestação de serviços ambulatoriais na area de oftalmologia aos usuarios do SUS conforme contrato.",
  "itens": [
   {
    "descricao": "CONVERSAO",
    "quantidade": "1.00",
    "valor_unitario": "607.172,40",
    "valor_total": "607.172,40"
   }
  ]
 },
 {
  "instituicao": "PREFEITURA MUNICIPAL DO NATAL",
  "orgao": "SECRETARIA MUNICIPAL DE SAUDE",
  "credor": "70.150.750/0001-25 - CENTRO DE CIRURGIA DE OLHOS DO RN",
  "empenhado": "R$ 285.041,92",
  "anulado": "R$ 0,00",
  "liquidado": "R$ 0,00",
  "pago": "R$ 0,00",
  "elemento": "OUTROS SERVICOS DE TERCEIROS-PESSOA JURIDICA",
  "numero": "204901223 / 2014",
  "data": "15/10/2014",
  "historico": "O presente instrumento tem por objeto a prestação de serviços ambulatoriais especializados na área de oftalmologia, conforme contrato firmado.",
  "itens": [
   {
    "descricao": "CONVERSAO",
    "quantidade": "1.00",
    "valor_unitario": "285.041,92",
    "valor_total": "285.041,92"
   }
  ]
 },
 {
  "instituicao": "PREFEITURA MUNICIPAL DO NATAL",
  "orgao": "SECRETARIA MUNICIPAL DE SAUDE",
  "credor": "70.150.750/0001-25 - CENTRO DE CIRURGIA DE OLHOS DO RN",
  "empenhado": "R$ 1.594.560,72",
  "anulado": "R$ 151.214,55",
  "liquidado": "R$ 1.443.346,17",
  "pago": "R$ 151.214,55",
  "elemento": "OUTROS SERVICOS DE TERCEIROS-PESSOA JURIDICA",
  "numero": "204900063 / 2014",
  "data": "20/01/2014",
  "historico": "Referente a prestação de serviços aos usuarios do SUS na area de oftalmologia conforme contrato.",
  "itens": [
   {
    "descricao": "CONVERSAO",
    "quantidade": "1.00",
    "valor_unitario": "1.594.560,72",
    "valor_total": "1.594.560,72"
   }
  ]
 },
 {
  "instituicao": "PREFEITURA MUNICIPAL DO NATAL",
  "orgao": "SECRETARIA MUNICIPAL DE SAUDE",
  "credor": "08.823.611/0001-41 - FACO CONSTRUCOES LTDA ME",
  "empenhado": "R$ 248.720,03",
  "anulado": "R$ 0,00",
  "liquidado": "R$ 209.704,47",
  "pago": "R$ 0,00",
  "elemento": "OUTROS SERVICOS DE TERCEIROS- PESSOA JURIDICA",
  "numero": "204900317 / 2014",
  "data": "21/02/2014",
  "historico": "Este instrumento tem por objetivo o empenho, para cobrir o 1º termo aditivo, referente a 1ª adequação constante nas fls. 14 e 15 do processo 52220/2013-53.",
  "itens": [
   {
    "descricao": "CONVERSAO",
    "quantidade": "1.00",
    "valor_unitario": "248.720,03",
    "valor_total": "248.720,03"
   }
  ]
 },
 {
  "instituicao": "PREFEITURA MUNICIPAL DO NATAL",
  "orgao": "SECRETARIA MUNICIPAL DE SAUDE",
  "credor": "19.748.440/0001-50 - G2 CONSTRUTORA E INCORPORADORA LTDA-EPP",
  "empenhado": "R$ 12.000,00",
  "anulado": "R$ 0,00",
  "liquidado": "R$ 0,00",
  "pago": "R$ 0,00",
  "elemento": "OUTROS SERVICOS DE TERCEIROS- PESSOA JURIDICA",
  "numero": "204901557 / 2014",
  "data": "18/12/2014",
  "historico": "A presente nota de empenho tem por objeto, o acréscimo de 45,35% (quarenta e cinco vírgula trinta e cinco por cento) do valor inicialmente pactuado para fins de execução dos serviços, de reforma de Centro de Referencia Odontologia Dr. Norton Mariz, observando Contrato firmado entre as partes.",
  "itens": [
   {
    "descricao": "CONVERSAO",
    "quantidade": "1.00",
    "valor_unitario": "12.000,00",
    "valor_total": "12.000,00"
   }
  ]
 },
 {
  "instituicao": "PREFEITURA MUNICIPAL DO NATAL",
  "orgao": "SECRETARIA MUNICIPAL DE SAUDE",
  "credor": "19.748.440/0001-50 - G2 CONSTRUTORA E INCORPORADORA LTDA-EPP",
  "empenhado": "R$ 70.264,31",
  "anulado": "R$ 0,00",
  "liquidado": "R$ 46.839,06",
  "pago": "R$ 0,00",
  "elemento": "OUTROS SERVICOS DE TERCEIROS- PESSOA JURIDICA",
  "numero": "204901148 / 2014",
  "data": "19/09/2014",
  "historico": "O presente instrumento tem por objeto a contratação de empresa para execução de serviços de reforma no Centro de Referencia Odontológica Dr. Morto Mariz, nos termos deste Contrato e suas Cláusulas.",
  "itens": [
   {
    "descricao": "CONVERSAO",
    "quantidade": "1.00",
    "valor_unitario": "70.264,31",
    "valor_total": "70.264,31"
   }
  ]
 },
 {
  "instituicao": "PREFEITURA MUNICIPAL DO NATAL",
  "orgao": "SECRETARIA MUNICIPAL DE SAUDE",
  "credor": "19.748.440/0001-50 - G2 CONSTRUTORA E INCORPORADORA LTDA-EPP",
  "empenhado": "R$ 251.741,94",
  "anulado": "R$ 0,00",
  "liquidado": "R$ 30.541,11",
  "pago": "R$ 0,00",
  "elemento": "OUTROS SERVICOS DE TERCEIROS- PESSOA JURIDICA",
  "numero": "204901147 / 2014",
  "data": "19/09/2014",
  "historico": "O presente instrumento tem por objeto a contratação de empresa para execução de serviços de reforma na unidade de Saúde de Lagoa Seca, nos termos deste Contrato e suas Cláusulas.",
  "itens": [
   {
    "descricao": "CONVERSAO",
    "quantidade": "1.00",
    "valor_unitario": "251.741,94",
    "valor_total": "251.741,94"
   }
  ]
 },
 {
  "instituicao": "PREFEITURA MUNICIPAL DO NATAL",
  "orgao": "SECRETARIA MUNICIPAL DE SAUDE",
  "credor": "04.325.158/0001-92 - MILLENIUM CONSTRUÇÃO CIVIL LTDA-ME.",
  "empenhado": "R$ 14.985,63",
  "anulado": "R$ 0,00",
  "liquidado": "R$ 14.985,63",
  "pago": "R$ 0,00",
  "elemento": "OUTROS SERVICOS DE TERCEIROS- PESSOA JURIDICA",
  "numero": "204901024 / 2014",
  "data": "03/09/2014",
  "historico": "O presente instrumento tem por objeto a prestação de serviços de reforma da USF km 06, solicitado no Memorando nº 63/2014 e ainda conforme contrato firmado.",
  "itens": [
   {
    "descricao": "CONVERSAO",
    "quantidade": "1.00",
    "valor_unitario": "14.985,63",
    "valor_total": "14.985,63"
   }
  ]
 },
 {
  "instituicao": "PREFEITURA MUNICIPAL DO NATAL",
  "orgao": "SECRETARIA MUNICIPAL DE SAUDE",
  "credor": "05.619.190/0001-43 - MMC - CONSTRUÇÕES E EMPREENDIMENTOS LTDA",
  "empenhado": "R$ 4.996,37",
  "anulado": "R$ 0,00",
  "liquidado": "R$ 0,00",
  "pago": "R$ 0,00",
  "elemento": "OUTROS SERVICOS DE TERCEIROS- PESSOA JURIDICA",
  "numero": "204901588 / 2014",
  "data": "23/12/2014",
  "historico": "O presente instrumento tem por objeto a prestação de serviços de engenharia visando à manutenção preventiva e corretiva das estruturas dos imóveis, conforme Contrato firmado entre as partes, lote III.",
  "itens": [
   {
    "descricao": "CONVERSAO",
    "quantidade": "1.00",
    "valor_unitario": "4.996,37",
    "valor_total": "4.996,37"
   }
  ]
 },
 {
  "instituicao": "PREFEITURA MUNICIPAL DO NATAL",
  "orgao": "SECRETARIA MUNICIPAL DE SAUDE",
  "credor": "05.619.190/0001-43 - MMC - CONSTRUÇÕES E EMPREENDIMENTOS LTDA",
  "empenhado": "R$ 19.985,49",
  "anulado": "R$ 0,00",
  "liquidado": "R$ 0,00",
  "pago": "R$ 0,00",
  "elemento": "OUTROS SERVICOS DE TERCEIROS- PESSOA JURIDICA",
  "numero": "204901587 / 2014",
  "data": "23/12/2014",
  "historico": "O presente instrumento tem por objeto a prestação de serviços de engenharia visando à manutenção preventiva e corretiva das estruturas dos imóveis,conforme Contrato firmado, lote III.",
  "itens": [
   {
    "descricao": "CONVERSAO",
    "quantidade": "1.00",
    "valor_unitario": "19.985,49",
    "valor_total": "19.985,49"
   }
  ]
 },
 {
  "instituicao": "PREFEITURA MUNICIPAL DO NATAL",
  "orgao": "SECRETARIA MUNICIPAL DE SAUDE",
  "credor": "05.619.190/0001-43 - MMC - CONSTRUÇÕES E EMPREENDIMENTOS LTDA",
  "empenhado": "R$ 3.568,84",
  "anulado": "R$ 0,00",
  "liquidado": "R$ 1.438,07",
  "pago": "R$ 0,00",
  "elemento": "OUTROS SERVICOS DE TERCEIROS- PESSOA JURIDICA",
  "numero": "204901586 / 2014",
  "data": "23/12/2014",
  "historico": "O presente instrumento tem por objeto a prestação de serviços de engenharia visando a manutenção preventiva e corretiva das estruturas físicas dos imóveis, conforme contrato firmado, lote III.",
  "itens": [
   {
    "descricao": "CONVERSAO",
    "quantidade": "1.00",
    "valor_unitario": "3.568,84",
    "valor_total": "3.568,84"
   }
  ]
 },
 {
  "instituicao": "PREFEITURA MUNICIPAL DO NATAL",
  "orgao": "SECRETARIA MUNICIPAL DE SAUDE",
  "credor": "05.619.190/0001-43 - MMC - CONSTRUÇÕES E EMPREENDIMENTOS LTDA",
  "empenhado": "R$ 74.945,58",
  "anulado": "R$ 0,00",
  "liquidado": "R$ 22.933,76",
  "pago": "R$ 0,00",
  "elemento": "OUTROS SERVICOS DE TERCEIROS- PESSOA JURIDICA",
  "numero": "204901584 / 2014",
  "data": "23/12/2014",
  "historico": "O presente instrumento tem por objeto a prestação de serviços de engenharia visando à manutenção preventiva e corretiva das estruturas dos imóveis,conforme Contrato firmado, lote III.",
  "itens": [
   {
    "descricao": "CONVERSAO",
    "quantidade": "1.00",
    "valor_unitario": "74.945,58",
    "valor_total": "74.945,58"
   }
  ]
 },
 {
  "instituicao": "PREFEITURA MUNICIPAL DO NATAL",
  "orgao": "SECRETARIA MUNICIPAL DE SAUDE",
  "credor": "05.619.190/0001-43 - MMC - CONSTRUÇÕES E EMPREENDIMENTOS LTDA",
  "empenhado": "R$ 17.844,19",
  "anulado": "R$ 0,00",
  "liquidado": "R$ 0,00",
  "pago": "R$ 0,00",
  "elemento": "OUTROS SERVICOS DE TERCEIROS- PESSOA JURIDICA",
  "numero": "204901582 / 2014",
  "data": "23/12/2014",
  "historico": "O presente instrumento tem por objeto a prestação de serviços de engenharia visando a manutenção preventiva e corretiva das estruturas físicas dos imóveis, conforme contrato firmado, lote III.",
  "itens": []
 },
 {
  "instituicao": "PREFEITURA MUNICIPAL DO NATAL",
  "orgao": "SECRETARIA MUNICIPAL DE SAUDE",
  "credor": "05.619.190/0001-43 - MMC - CONSTRUÇÕES E EMPREENDIMENTOS LTDA",
  "empenhado": "R$ 39.257,21",
  "anulado": "R$ 0,00",
  "liquidado": "R$ 39.257,21",
  "pago": "R$ 0,00",
  "elemento": "OUTROS SERVICOS DE TERCEIROS- PESSOA JURIDICA",
  "numero": "204901580 / 2014",
  "data": "23/12/2014",
  "historico": "O presente instrumento tem por objeto a prestação de serviços de engenharia visando à manutenção preventiva e corretiva das estruturas físicas dos imóveis, conforme contrato firmado, lote III.",
  "itens": [
   {
    "descricao": "CONVERSAO",
    "quantidade": "1.00",
    "valor_unitario": "39.257,21",
    "valor_total": "39.257,21"
   }
  ]
 },
 {
  "instituicao": "PREFEITURA MUNICIPAL DO NATAL",
  "orgao": "SECRETARIA MUNICIPAL DE SAUDE",
  "credor": "08.573.845/0001-88 - MODERNA ENGENHARIA",
  "empenhado": "R$ 14.575,27",
  "anulado": "R$ 0,00",
  "liquidado": "R$ 14.575,27",
  "pago": "R$ 0,00",
  "elemento": "OUTROS SERVICOS DE TERCEIROS- PESSOA JURIDICA",
  "numero": "204901305 / 2014",
  "data": "05/11/2014",
  "historico": "O presente instrumento tem por objeto a prestação de serviços de construção e reparo, no muro da Unidade de Saúde da Família em Santarém, observando entre outras a Cláusula 05, do Contrato firmado entre as partes.",
  "itens": [
   {
    "descricao": "CONVERSAO",
    "quantidade": "1.00",
    "valor_unitario": "14.575,27",
    "valor_total": "14.575,27"
   }
  ]
 },
 {
  "instituicao": "PREFEITURA MUNICIPAL DO NATAL",
  "orgao": "SECRETARIA MUNICIPAL DE SAUDE",
  "credor": "05.346.248/0001-22 - PLANA EDIFICAÇÕES LTDA",
  "empenhado": "R$ 464.311,09",
  "anulado": "R$ 0,00",
  "liquidado": "R$ 0,00",
  "pago": "R$ 0,00",
  "elemento": "OUTROS SERVICOS DE TERCEIROS- PESSOA JURIDICA",
  "numero": "204901319 / 2014",
  "data": "11/11/2014",
  "historico": "O presente instrumento tem por objeto a prestação de serviços de reforma da Unidade Básica de Felipe Camarão II, conforme contrato firmado.",
  "itens": [
   {
    "descricao": "CONVERSAO",
    "quantidade": "1.00",
    "valor_unitario": "464.311,09",
    "valor_total": "464.311,09"
   }
  ]
 },
 {
  "instituicao": "PREFEITURA MUNICIPAL DO NATAL",
  "orgao": "SECRETARIA MUNICIPAL DE SAUDE",
  "credor": "05.346.248/0001-22 - PLANA EDIFICAÇÕES LTDA",
  "empenhado": "R$ 154.770,36",
  "anulado": "R$ 0,00",
  "liquidado": "R$ 0,00",
  "pago": "R$ 0,00",
  "elemento": "OUTROS SERVICOS DE TERCEIROS- PESSOA JURIDICA",
  "numero": "204901318 / 2014",
  "data": "11/11/2014",
  "historico": "O presente instrumento tem por objeto a prestação de serviços de reforma da Unidade Básica de Felipe Camarão II, conforme contrato firmado.",
  "itens": [
   {
    "descricao": "CONVERSAO",
    "quantidade": "1.00",
    "valor_unitario": "154.770,36",
    "valor_total": "154.770,36"
   }
  ]
 },
 {
  "instituicao": "PREFEITURA MUNICIPAL DO NATAL",
  "orgao": "SECRETARIA MUNICIPAL DE SAUDE",
  "credor": "04.895.340/0001-89 - RVV CONSTRUÇÕES E EMPREENDIMENTOS LTDA",
  "empenhado": "R$ 3.005,48",
  "anulado": "R$ 0,00",
  "liquidado": "R$ 0,00",
  "pago": "R$ 0,00",
  "elemento": "OUTROS SERVICOS DE TERCEIROS- PESSOA JURIDICA",
  "numero": "204901434 / 2014",
  "data": "28/11/2014",
  "historico": "O presente instrumento tem por objeto a prestação de serviços de engenharia visando à manutenção preventiva e corretiva das estruturas físicas dos imóveis (alugados e próprios) da rede de saúde da cidade do Natal.",
  "itens": [
   {
    "descricao": "CONVERSAO",
    "quantidade": "1.00",
    "valor_unitario": "3.005,48",
    "valor_total": "3.005,48"
   }
  ]
 },
 {
  "instituicao": "PREFEITURA MUNICIPAL DO NATAL",
  "orgao": "SECRETARIA MUNICIPAL DE SAUDE",
  "credor": "04.895.340/0001-89 - RVV CONSTRUÇÕES E EMPREENDIMENTOS LTDA",
  "empenhado": "R$ 15.027,37",
  "anulado": "R$ 0,00",
  "liquidado": "R$ 14.027,87",
  "pago": "R$ 0,00",
  "elemento": "OUTROS SERVICOS DE TERCEIROS- PESSOA JURIDICA",
  "numero": "204901431 / 2014",
  "data": "28/11/2014",
  "historico": "O presente instrumento tem por objeto a prestação de serviços de engenharia visando à manutenção preventiva e corretiva das estruturas físicas dos imóveis (alugados e próprios) da rede de saúde da cidade do Natal.",
  "itens": [
   {
    "descricao": "CONVERSAO",
    "quantidade": "1.00",
    "valor_unitario": "15.027,37",
    "valor_total": "15.027,37"
   }
  ]
 },
 {
  "instituicao": "PREFEITURA MUNICIPAL DO NATAL",
  "orgao": "SECRETARIA MUNICIPAL DE SAUDE",
  "credor": "04.895.340/0001-89 - RVV CONSTRUÇÕES E EMPREENDIMENTOS LTDA",
  "empenhado": "R$ 4.207,66",
  "anulado": "R$ 0,00",
  "liquidado": "R$ 4.207,66",
  "pago": "R$ 0,00",
  "elemento": "OUTROS SERVICOS DE TERCEIROS- PESSOA JURIDICA",
  "numero": "204901430 / 2014",
  "data": "28/11/2014",
  "historico": "O presente instrumento tem por objeto a prestação de serviços de engenharia visando à manutenção preventiva e corretiva das estruturas físicas dos imóveis (alugados e próprios) da rede de saúde da cidade do Natal.",
  "itens": [
   {
    "descricao": "CONVERSAO",
    "quantidade": "1.00",
    "valor_unitario": "4.207,66",
    "valor_total": "4.207,66"
   }
  ]
 },
 {
  "instituicao": "PREFEITURA MUNICIPAL DO NATAL",
  "orgao": "SECRETARIA MUNICIPAL DE SAUDE",
  "credor": "04.895.340/0001-89 - RVV CONSTRUÇÕES E EMPREENDIMENTOS LTDA",
  "empenhado": "R$ 63.114,96",
  "anulado": "R$ 0,00",
  "liquidado": "R$ 63.114,96",
  "pago": "R$ 0,00",
  "elemento": "OUTROS SERVICOS DE TERCEIROS- PESSOA JURIDICA",
  "numero": "204901428 / 2014",
  "data": "28/11/2014",
  "historico": "O presente instrumento tem por objeto a prestação de serviços de engenharia visando à manutenção preventiva e corretiva das estruturas físicas dos imóveis (alugados e próprios) da rede de saúde da cidade do Natal.",
  "itens": [
   {
    "descricao": "CONVERSAO",
    "quantidade": "1.00",
    "valor_unitario": "63.114,96",
    "valor_total": "63.114,96"
   }
  ]
 },
 {
  "instituicao": "PREFEITURA MUNICIPAL DO NATAL",
  "orgao": "SECRETARIA MUNICIPAL DE SAUDE",
  "credor": "04.895.340/0001-89 - RVV CONSTRUÇÕES E EMPREENDIMENTOS LTDA",
  "empenhado": "R$ 132.240,87",
  "anulado": "R$ 0,00",
  "liquidado": "R$ 132.240,87",
  "pago": "R$ 0,00",
  "elemento": "OUTROS SERVICOS DE TERCEIROS- PESSOA JURIDICA",
  "numero": "204901426 / 2014",
  "data": "28/11/2014",
  "historico": "O presente instrumento tem por objeto a prestação de serviços de engenharia visando à manutenção preventiva e corretiva das estruturas físicas dos imóveis (alugados e próprios) da rede de saúde da cidade do Natal.",
  "itens": [
   {
    "descricao": "CONVERSAO",
    "quantidade": "1.00",
    "valor_unitario": "132.240,87",
    "valor_total": "132.240,87"
   }
  ]
 },
 {
  "instituicao": "PREFEITURA MUNICIPAL DO NATAL",
  "orgao": "SECRETARIA MUNICIPAL DE SAUDE",
  "credor": "04.895.340/0001-89 - RVV CONSTRUÇÕES E EMPREENDIMENTOS LTDA",
  "empenhado": "R$ 40.793,01",
  "anulado": "R$ 15.060,75",
  "liquidado": "R$ 25.732,26",
  "pago": "R$ 15.060,75",
  "elemento": "OUTROS SERVICOS DE TERCEIROS- PESSOA JURIDICA",
  "numero": "204900735 / 2014",
  "data": "03/07/2014",
  "historico": "Empenho feito em conformidade com a instrução técnica nº 23260/2014 - DCI/CGM, fl. 109, item 01, no que tange aos serviços de reforma.",
  "itens": [
   {
    "descricao": "CONVERSAO",
    "quantidade": "1.00",
    "valor_unitario": "40.793,01",
    "valor_total": "40.793,01"
   }
  ]
 },
 {
  "instituicao": "PREFEITURA MUNICIPAL DO NATAL",
  "orgao": "SECRETARIA MUNICIPAL DE SAUDE",
  "credor": "04.895.340/0001-89 - RVV CONSTRUÇÕES E EMPREENDIMENTOS LTDA",
  "empenhado": "R$ 62.171,04",
  "anulado": "R$ 40.793,01",
  "liquidado": "R$ 21.378,03",
  "pago": "R$ 40.793,01",
  "elemento": "OUTROS SERVICOS DE TERCEIROS- PESSOA JURIDICA",
  "numero": "204900225 / 2014",
  "data": "31/01/2014",
  "historico": "Referente a prestação de serviços de reforma, contemplando adequações na estrutura fisica entre outros conforme contrato.",
  "itens": [
   {
    "descricao": "CONVERSAO",
    "quantidade": "1.00",
    "valor_unitario": "62.171,04",
    "valor_total": "62.171,04"
   }
  ]
 },
 {
  "instituicao": "PREFEITURA MUNICIPAL DO NATAL",
  "orgao": "SECRETARIA MUNICIPAL DE SAUDE",
  "credor": "04.895.340/0001-89 - RVV CONSTRUÇÕES E EMPREENDIMENTOS LTDA",
  "empenhado": "R$ 357.027,24",
  "anulado": "R$ 0,00",
  "liquidado": "R$ 357.027,24",
  "pago": "R$ 0,00",
  "elemento": "OUTROS SERVICOS DE TERCEIROS- PESSOA JURIDICA",
  "numero": "204900198 / 2014",
  "data": "20/01/2014",
  "historico": "Referente a prestação de serviços de engenharia visando a manutenção preventiva e corretiva das estruturas fisicas dos imoveis\\nconforme contrato.",
  "itens": [
   {
    "descricao": "CONVERSAO",
    "quantidade": "1.00",
    "valor_unitario": "357.027,24",
    "valor_total": "357.027,24"
   }
  ]
 },
 {
  "instituicao": "PREFEITURA MUNICIPAL DO NATAL",
  "orgao": "SECRETARIA MUNICIPAL DE SAUDE",
  "credor": "04.895.340/0001-89 - RVV CONSTRUÇÕES E EMPREENDIMENTOS LTDA",
  "empenhado": "R$ 288.127,24",
  "anulado": "R$ 0,00",
  "liquidado": "R$ 288.127,24",
  "pago": "R$ 0,00",
  "elemento": "OUTROS SERVICOS DE TERCEIROS- PESSOA JURIDICA",
  "numero": "204900197 / 2014",
  "data": "20/01/2014",
  "historico": "Referente a prestação de serviços de engenharia visando a manutenção preventiva e corretiva das estruturas fisicas dos imoveis\\nconforme contrato.",
  "itens": [
   {
    "descricao": "CONVERSAO",
    "quantidade": "1.00",
    "valor_unitario": "288.127,24",
    "valor_total": "288.127,24"
   }
  ]
 },
 {
  "instituicao": "PREFEITURA MUNICIPAL DO NATAL",
  "orgao": "SECRETARIA MUNICIPAL DE SAUDE",
  "credor": "16.417.860/0001-65 - VALE & VALE CONSTRUÇÕES, SERVIÇOS E LOCA",
  "empenhado": "R$ 195.136,22",
  "anulado": "R$ 0,00",
  "liquidado": "R$ 140.819,64",
  "pago": "R$ 0,00",
  "elemento": "OUTROS SERVICOS DE TERCEIROS- PESSOA JURIDICA",
  "numero": "204901415 / 2014",
  "data": "25/11/2014",
  "historico": "O presente instrumento tem por objeto a mudança da fonte 183 para 111, em virtude de autorização por parte do Titular da Pasta da SMS, tendo em vista que a Secretaria está assumindo com recursos próprios a conclusão da obra da Empresa Vale & Vale Construções, Serviços e Locações LTDA, uma vez que o Contrato não foi renovado por falta da assinatura do Sr. Ney Lopes de Souza Júnior, Prefeito na época correspondente.",
  "itens": [
   {
    "descricao": "CONVERSAO",
    "quantidade": "1.00",
    "valor_unitario": "195.136,22",
    "valor_total": "195.136,22"
   }
  ]
 },
 {
  "instituicao": "PREFEITURA MUNICIPAL DO NATAL",
  "orgao": "SECRETARIA MUNICIPAL DE SAUDE",
  "credor": "16.417.860/0001-65 - VALE & VALE CONSTRUÇÕES, SERVIÇOS E LOCA",
  "empenhado": "R$ 6.099,88",
  "anulado": "R$ 0,00",
  "liquidado": "R$ 6.099,88",
  "pago": "R$ 0,00",
  "elemento": "OUTROS SERVICOS DE TERCEIROS- PESSOA JURIDICA",
  "numero": "204901240 / 2014",
  "data": "17/10/2014",
  "historico": "O presente instrumento tem por objeto o acréscimo de aproximadamente 22,55%, do valor inicialmente compactuado, conforme 2º Termo Aditivo ao Contrato 58/2014.",
  "itens": [
   {
    "descricao": "CONVERSAO",
    "quantidade": "1.00",
    "valor_unitario": "6.099,88",
    "valor_total": "6.099,88"
   }
  ]
 },
 {
  "instituicao": "PREFEITURA MUNICIPAL DO NATAL",
  "orgao": "SECRETARIA MUNICIPAL DE SAUDE",
  "credor": "16.417.860/0001-65 - VALE & VALE CONSTRUÇÕES, SERVIÇOS E LOCA",
  "empenhado": "R$ 54.898,95",
  "anulado": "R$ 0,00",
  "liquidado": "R$ 0,00",
  "pago": "R$ 0,00",
  "elemento": "OUTROS SERVICOS DE TERCEIROS- PESSOA JURIDICA",
  "numero": "204901239 / 2014",
  "data": "17/10/2014",
  "historico": "O presente instrumento tem por objeto o acréscimo de aproximadamente 22,55%, do valor inicialmente compactuado, conforme 2º Termo Aditivo ao Contrato 58/2014.",
  "itens": [
   {
    "descricao": "CONVERSAO",
    "quantidade": "1.00",
    "valor_unitario": "54.898,95",
    "valor_total": "54.898,95"
   }
  ]
 },
 {
  "instituicao": "PREFEITURA MUNICIPAL DO NATAL",
  "orgao": "SECRETARIA MUNICIPAL DE SAUDE",
  "credor": "16.417.860/0001-65 - VALE & VALE CONSTRUÇÕES, SERVIÇOS E LOCA",
  "empenhado": "R$ 27.049,48",
  "anulado": "R$ 0,00",
  "liquidado": "R$ 21.093,28",
  "pago": "R$ 0,00",
  "elemento": "OUTROS SERVICOS DE TERCEIROS- PESSOA JURIDICA",
  "numero": "204901015 / 2014",
  "data": "29/08/2014",
  "historico": "Prestação de serviços de reforma no Prédio da Maternidade Leide Morais, em conformidade com o Contrato de n.º 58/2014 e Instrução Técnica de n.º 26005/2014 - DCI/CGM, assinado pelo Titular da SMS nos autos do Processo de n.º 041084/2012-95.",
  "itens": [
   {
    "descricao": "CONVERSAO",
    "quantidade": "1.00",
    "valor_unitario": "27.049,48",
    "valor_total": "27.049,48"
   }
  ]
 },
 {
  "instituicao": "PREFEITURA MUNICIPAL DO NATAL",
  "orgao": "SECRETARIA MUNICIPAL DE SAUDE",
  "credor": "16.417.860/0001-65 - VALE & VALE CONSTRUÇÕES, SERVIÇOS E LOCA",
  "empenhado": "R$ 243.445,32",
  "anulado": "R$ 195.136,22",
  "liquidado": "R$ 48.309,10",
  "pago": "R$ 195.136,22",
  "elemento": "OUTROS SERVICOS DE TERCEIROS- PESSOA JURIDICA",
  "numero": "204901014 / 2014",
  "data": "29/08/2014",
  "historico": "Prestação de serviços de reforma no Prédio da Maternidade Leite Morais, em conformidade com o Contrato de n.º 58/2014 e Instrução Técnica de n.º 26005/2014 - DCI/CGM, assinado pelo Titular da SMS nos autos do Processo de n.º 041084/2012-95.",
  "itens": [
   {
    "descricao": "CONVERSAO",
    "quantidade": "1.00",
    "valor_unitario": "243.445,32",
    "valor_total": "243.445,32"
   }
  ]
 },
 {
  "instituicao": "PREFEITURA MUNICIPAL DO NATAL",
  "orgao": "SECRETARIA MUNICIPAL DE SAUDE",
  "credor": "16.417.860/0001-65 - VALE & VALE CONSTRUÇÕES, SERVIÇOS E LOCA",
  "empenhado": "R$ 243.445,32",
  "anulado": "R$ 243.445,32",
  "liquidado": "R$ 0,00",
  "pago": "R$ 243.445,32",
  "elemento": "OUTROS SERVICOS DE TERCEIROS- PESSOA JURIDICA",
  "numero": "204900574 / 2014",
  "data": "06/05/2014",
  "historico": "O presente instrumento tem por objetivo a prestação de serviços de reforma no prédio da Maternidade Leide Morais, conforme processo 41084/2012-95.",
  "itens": [
   {
    "descricao": "CONVERSAO",
    "quantidade": "1.00",
    "valor_unitario": "243.445,32",
    "valor_total": "243.445,32"
   }
  ]
 },
 {
  "instituicao": "PREFEITURA MUNICIPAL DO NATAL",
  "orgao": "SECRETARIA MUNICIPAL DE SAUDE",
  "credor": "16.417.860/0001-65 - VALE & VALE CONSTRUÇÕES, SERVIÇOS E LOCA",
  "empenhado": "R$ 242.793,23",
  "anulado": "R$ 0,00",
  "liquidado": "R$ 0,00",
  "pago": "R$ 0,00",
  "elemento": "OUTROS SERVICOS DE TERCEIROS- PESSOA JURIDICA",
  "numero": "204900573 / 2014",
  "data": "06/05/2014",
  "historico": "O presente instrumento tem por objetivo a prestação de serviços de reforma no prédio da Maternidade Leide Morais, conforme processo 41084/2012-95.",
  "itens": [
   {
    "descricao": "CONVERSAO",
    "quantidade": "1.00",
    "valor_unitario": "242.793,23",
    "valor_total": "242.793,23"
   }
  ]
 },
 {
  "instituicao": "PREFEITURA MUNICIPAL DO NATAL",
  "orgao": "SECRETARIA MUNICIPAL DE SAUDE",
  "credor": "16.417.860/0001-65 - VALE & VALE CONSTRUÇÕES, SERVIÇOS E LOCA",
  "empenhado": "R$ 27.049,48",
  "anulado": "R$ 27.049,48",
  "liquidado": "R$ 0,00",
  "pago": "R$ 27.049,48",
  "elemento": "OUTROS SERVICOS DE TERCEIROS- PESSOA JURIDICA",
  "numero": "204900572 / 2014",
  "data": "06/05/2014",
  "historico": "O presente instrumento tem por objetivo a prestação de serviços de reforma no prédio da Maternidade Leide Morais, conforme processo 41084/2012-95.",
  "itens": [
   {
    "descricao": "CONVERSAO",
    "quantidade": "1.00",
    "valor_unitario": "27.049,48",
    "valor_total": "27.049,48"
   }
  ]
 },
 {
  "instituicao": "PREFEITURA MUNICIPAL DO NATAL",
  "orgao": "SECRETARIA MUNICIPAL DE SAUDE",
  "credor": "000.000.000-00 - ALEXANDRE JACOME DE FARIAS",
  "empenhado": "R$ 38.933,35",
  "anulado": "R$ 0,00",
  "liquidado": "R$ 32.000,00",
  "pago": "R$ 0,00",
  "elemento": "OUTROS SERVICOS DE TERCEIROS - PESSOA FISICA",
  "numero": "204900954 / 2014",
  "data": "13/08/2014",
  "historico": "O presente instrumento tem por objeto a locação de um imóvel, localizado na Avenida Floriano Peixoto, 479, Petrópolis, Natal-RN observando e tomando como referencia o Contrato firmado entre as partes.",
  "itens": [
   {
    "descricao": "CONVERSAO",
    "quantidade": "1.00",
    "valor_unitario": "38.933,35",
    "valor_total": "38.933,35"
   }
  ]
 },
 {
  "instituicao": "PREFEITURA MUNICIPAL DO NATAL",
  "orgao": "SECRETARIA MUNICIPAL DE SAUDE",
  "credor": "000.000.000-00 - ALEXANDRE JACOME DE FARIAS",
  "empenhado": "R$ 38.933,35",
  "anulado": "R$ 0,00",
  "liquidado": "R$ 32.000,00",
  "pago": "R$ 0,00",
  "elemento": "OUTROS SERVICOS DE TERCEIROS - PESSOA FISICA",
  "numero": "204900953 / 2014",
  "data": "13/08/2014",
  "historico": "O presente instrumento tem por objeto a locação de um imóvel, localizado na Avenida Floriano Peixoto, 479, Petrópolis, Natal-RN observando e tomando como referencia o Contrato firmado entre as partes.",
  "itens": [
   {
    "descricao": "CONVERSAO",
    "quantidade": "1.00",
    "valor_unitario": "38.933,35",
    "valor_total": "38.933,35"
   }
  ]
 },
 {
  "instituicao": "PREFEITURA MUNICIPAL DO NATAL",
  "orgao": "SECRETARIA MUNICIPAL DE SAUDE",
  "credor": "000.000.000-00 - ALEXANDRE JACOME DE FARIAS",
  "empenhado": "R$ 32.553,97",
  "anulado": "R$ 0,00",
  "liquidado": "R$ 32.553,97",
  "pago": "R$ 0,00",
  "elemento": "OUTROS SERVICOS DE TERCEIROS - PESSOA FISICA",
  "numero": "204900171 / 2014",
  "data": "20/01/2014",
  "historico": "O presente instrumento tem por objetivo cobrir as despesas referente a 03(três) meses e 02(dois) dias do atual exercício 2014, quanto a locação de imóvel, situado a Av. Floriano Peixoto, 479, Petropolis, Natal-RN, para funcionamento do DVS, conforme folha em anexo, repassado pela Coordenadoria Administrativa Núcleo de Contrato, como também do contrato firmado.",
  "itens": [
   {
    "descricao": "CONVERSAO",
    "quantidade": "1.00",
    "valor_unitario": "32.553,97",
    "valor_total": "32.553,97"
   }
  ]
 },
 {
  "instituicao": "PREFEITURA MUNICIPAL DO NATAL",
  "orgao": "SECRETARIA MUNICIPAL DE SAUDE",
  "credor": "000.000.000-00 - ALEXANDRE JACOME DE FARIAS",
  "empenhado": "R$ 19.532,38",
  "anulado": "R$ 0,00",
  "liquidado": "R$ 19.532,38",
  "pago": "R$ 0,00",
  "elemento": "OUTROS SERVICOS DE TERCEIROS - PESSOA FISICA",
  "numero": "204900170 / 2014",
  "data": "20/01/2014",
  "historico": "O presente instrumento tem por objetivo cobrir as despesas referente a 03(três) meses e 02(dois) dias do atual exercício 2014, quanto a locação de imóvel, situado a Av. Floriado Peixoto, 479, Petrópolis, Natal-RN, para funcionamento do DVS, conforme folha em anexo, repassado pela Coordenadoria Administrativa Núcleo de Contrato e contrato firmado.",
  "itens": [
   {
    "descricao": "CONVERSAO",
    "quantidade": "1.00",
    "valor_unitario": "19.532,38",
    "valor_total": "19.532,38"
   }
  ]
 },
 {
  "instituicao": "PREFEITURA MUNICIPAL DO NATAL",
  "orgao": "SECRETARIA MUNICIPAL DE SAUDE",
  "credor": "000.000.000-00 - ALINA SAMARA FARIAS GINANI",
  "empenhado": "R$ 24.000,00",
  "anulado": "R$ 21.340,00",
  "liquidado": "R$ 2.660,00",
  "pago": "R$ 21.340,00",
  "elemento": "OUTROS SERVICOS DE TERCEIROS - PESSOA FISICA",
  "numero": "204900206 / 2014",
  "data": "31/01/2014",
  "historico": "Referente despesa com estagiarios da Folha de Pagamento do exercício de 2014.",
  "itens": [
   {
    "descricao": "CONVERSAO",
    "quantidade": "1.00",
    "valor_unitario": "24.000,00",
    "valor_total": "24.000,00"
   }
  ]
 },
 {
  "instituicao": "PREFEITURA MUNICIPAL DO NATAL",
  "orgao": "SECRETARIA MUNICIPAL DE SAUDE",
  "credor": "000.000.000-00 - EDNA MARIA PIMENTEL GUEDES MARTINS",
  "empenhado": "R$ 50.333,33",
  "anulado": "R$ 333,33",
  "liquidado": "R$ 50.000,00",
  "pago": "R$ 333,33",
  "elemento": "OUTROS SERVICOS DE TERCEIROS - PESSOA FISICA",
  "numero": "204900419 / 2014",
  "data": "17/03/2014",
  "historico": "Locação de imóvel situado a Rua Almeida Castro, 1019, Tirol, Natal-RN.",
  "itens": [
   {
    "descricao": "CONVERSAO",
    "quantidade": "1.00",
    "valor_unitario": "50.333,33",
    "valor_total": "50.333,33"
   }
  ]
 },
 {
  "instituicao": "PREFEITURA MUNICIPAL DO NATAL",
  "orgao": "SECRETARIA MUNICIPAL DE SAUDE",
  "credor": "000.000.000-00 - EDNA MARIA PIMENTEL GUEDES MARTINS",
  "empenhado": "R$ 10.000,00",
  "anulado": "R$ 0,00",
  "liquidado": "R$ 10.000,00",
  "pago": "R$ 0,00",
  "elemento": "OUTROS SERVICOS DE TERCEIROS - PESSOA FISICA",
  "numero": "204900054 / 2014",
  "data": "20/01/2014",
  "historico": "Locação de imóvel, situado à rua Almeida Castro, 1019, Tirol. . Empenho feito conforme folha em anexo, contrato firmado 19/2013, repassado pelo Coordenadoria Administrativa Núcleo de Contratos.",
  "itens": [
   {
    "descricao": "CONVERSAO",
    "quantidade": "1.00",
    "valor_unitario": "10.000,00",
    "valor_total": "10.000,00"
   }
  ]
 },
 {
  "instituicao": "PREFEITURA MUNICIPAL DO NATAL",
  "orgao": "SECRETARIA MUNICIPAL DE SAUDE",
  "credor": "000.000.000-00 - ELENITA DE LIMA FIGUEIREDO",
  "empenhado": "R$ 25.029,00",
  "anulado": "R$ 0,00",
  "liquidado": "R$ 25.029,00",
  "pago": "R$ 0,00",
  "elemento": "OUTROS SERVICOS DE TERCEIROS - PESSOA FISICA",
  "numero": "204900518 / 2014",
  "data": "07/04/2014",
  "historico": "o presente instrumento tem por objetivo a locação do imóvel destinado ao funcionamento da Unidade de Saúde da Família de Nordelândia, conforme contrato firmado.",
  "itens": [
   {
    "descricao": "CONVERSAO",
    "quantidade": "1.00",
    "valor_unitario": "25.029,00",
    "valor_total": "25.029,00"
   }
  ]
 },
 {
  "instituicao": "PREFEITURA MUNICIPAL DO NATAL",
  "orgao": "SECRETARIA MUNICIPAL DE SAUDE",
  "credor": "000.000.000-00 - ELMA MEDEIROS DE FIGUEREDO",
  "empenhado": "R$ 27.324,00",
  "anulado": "R$ 0,00",
  "liquidado": "R$ 27.324,00",
  "pago": "R$ 0,00",
  "elemento": "OUTROS SERVICOS DE TERCEIROS - PESSOA FISICA",
  "numero": "204900673 / 2014",
  "data": "11/06/2014",
  "historico": "O presente instrumento por objetivo a locação do imóvel destinado ao funcionamento do Centro de Atenção Psicossocial - CAPS OESTE. conforme aditivo firmado.",
  "itens": [
   {
    "descricao": "CONVERSAO",
    "quantidade": "1.00",
    "valor_unitario": "27.324,00",
    "valor_total": "27.324,00"
   }
  ]
 },
 {
  "instituicao": "PREFEITURA MUNICIPAL DO NATAL",
  "orgao": "SECRETARIA MUNICIPAL DE SAUDE",
  "credor": "000.000.000-00 - ELMA MEDEIROS DE FIGUEREDO",
  "empenhado": "R$ 24.156,00",
  "anulado": "R$ 3.960,00",
  "liquidado": "R$ 20.196,00",
  "pago": "R$ 3.960,00",
  "elemento": "OUTROS SERVICOS DE TERCEIROS - PESSOA FISICA",
  "numero": "204900061 / 2014",
  "data": "20/01/2014",
  "historico": "Locação de imóvel situado à rua Murilo de Melo, 1924, Bairro - Lagoa Nova, Natal, destinado ao funcionamento do Centro de Atenção Psicosocial Oeste-CAPS. Empenho feito conforme folha em anexo, contrato firmado 60/2013, repassado pelo Coordenadoria Administrativa Núcleo de Contratos.",
  "itens": [
   {
    "descricao": "CONVERSAO",
    "quantidade": "1.00",
    "valor_unitario": "24.156,00",
    "valor_total": "24.156,00"
   }
  ]
 },
 {
  "instituicao": "PREFEITURA MUNICIPAL DO NATAL",
  "orgao": "SECRETARIA MUNICIPAL DE SAUDE",
  "credor": "000.000.000-00 - ESMERALDA SILVA DOS REIS CAVALCANTE",
  "empenhado": "R$ 6.513,84",
  "anulado": "R$ 0,00",
  "liquidado": "R$ 6.513,84",
  "pago": "R$ 0,00",
  "elemento": "OUTROS SERVICOS DE TERCEIROS - PESSOA FISICA",
  "numero": "204900929 / 2014",
  "data": "08/08/2014",
  "historico": "O presente instrumento tem por objeto o pagamento por despesa de exercício anterior, em conformidade com a fl. 32 nos meses especificados e ano corrente..",
  "itens": [
   {
    "descricao": "CONVERSAO",
    "quantidade": "1.00",
    "valor_unitario": "6.513,84",
    "valor_total": "6.513,84"
   }
  ]
 },
 {
  "instituicao": "PREFEITURA MUNICIPAL DO NATAL",
  "orgao": "SECRETARIA MUNICIPAL DE SAUDE",
  "credor": "000.000.000-00 - FRANCISCO GIORDANDOFRANCA DA SILVA",
  "empenhado": "R$ 7.536,00",
  "anulado": "R$ 0,00",
  "liquidado": "R$ 7.536,00",
  "pago": "R$ 0,00",
  "elemento": "OUTROS SERVICOS DE TERCEIROS - PESSOA FISICA",
  "numero": "204901012 / 2014",
  "data": "29/08/2014",
  "historico": "O presente instrumento tem por objeto, a locação de imóvel que destina-se exclusivamente para servir como sede do Distrito Sanitário Norte I, observando principalmente entre outras as Cláusulas quarta - Vigência e Cláusula quinta - valor.",
  "itens": [
   {
    "descricao": "CONVERSAO",
    "quantidade": "1.00",
    "valor_unitario": "7.536,00",
    "valor_total": "7.536,00"
   }
  ]
 },
 {
  "instituicao": "PREFEITURA MUNICIPAL DO NATAL",
  "orgao": "SECRETARIA MUNICIPAL DE SAUDE",
  "credor": "000.000.000-00 - FRANCISCO SABINO DA CAMARA E S",
  "empenhado": "R$ 9.999,54",
  "anulado": "R$ 0,00",
  "liquidado": "R$ 8.888,48",
  "pago": "R$ 0,00",
  "elemento": "OUTROS SERVICOS DE TERCEIROS - PESSOA FISICA",
  "numero": "204900536 / 2014",
  "data": "10/04/2014",
  "historico": "O presente tem por objetivo o pagamento quanto a renovação contratual de imóvel, destinado a Unidade de Saúde da Família - USF Pompéia, solicitado através do memo de n.º 216/2013 - D.S. Norte I, em conformidade com o despacho da ASSEJUR/SMS às fls. 42 e 43, autorizado pelo Titular da Pasta da SMS, fl. 52 do Processo de n.º 037705/2013-17.",
  "itens": []
 },
 {
  "instituicao": "PREFEITURA MUNICIPAL DO NATAL",
  "orgao": "SECRETARIA MUNICIPAL DE SAUDE",
  "credor": "000.000.000-00 - GUIOMAR DE ROCHA MEDEIROS",
  "empenhado": "R$ 1.920,00",
  "anulado": "R$ 0,00",
  "liquidado": "R$ 0,00",
  "pago": "R$ 0,00",
  "elemento": "OUTROS SERVICOS DE TERCEIROS - PESSOA FISICA",
  "numero": "204901646 / 2014",
  "data": "31/12/2014",
  "historico": "O presente instrumento tem por objeto a locação de imóvel, junto a Senhora Guiomar da Rocha Medeiros, referente ao mês de dezembro do atual do exercício.",
  "itens": [
   {
    "descricao": "CONVERSAO",
    "quantidade": "1.00",
    "valor_unitario": "1.920,00",
    "valor_total": "1.920,00"
   }
  ]
 },
 {
  "instituicao": "PREFEITURA MUNICIPAL DO NATAL",
  "orgao": "SECRETARIA MUNICIPAL DE SAUDE",
  "credor": "000.000.000-00 - GUIOMAR DE ROCHA MEDEIROS",
  "empenhado": "R$ 7.200,00",
  "anulado": "R$ 0,00",
  "liquidado": "R$ 7.200,00",
  "pago": "R$ 0,00",
  "elemento": "OUTROS SERVICOS DE TERCEIROS - PESSOA FISICA",
  "numero": "204901596 / 2014",
  "data": "26/12/2014",
  "historico": "Locação de imóvel junto a Srª GUIOMAR DA ROCHA MEDEIROS, em conformidade com o Parecer Jurídico de n.º 1145/2014 contido nas folhas 182 a 189 do Processo de n.º 054000/2013-64.",
  "itens": [
   {
    "descricao": "CONVERSAO",
    "quantidade": "1.00",
    "valor_unitario": "7.200,00",
    "valor_total": "7.200,00"
   }
  ]
 },
 {
  "instituicao": "PREFEITURA MUNICIPAL DO NATAL",
  "orgao": "SECRETARIA MUNICIPAL DE SAUDE",
  "credor": "000.000.000-00 - GUIOMAR DE ROCHA MEDEIROS",
  "empenhado": "R$ 14.400,00",
  "anulado": "R$ 0,00",
  "liquidado": "R$ 14.400,00",
  "pago": "R$ 0,00",
  "elemento": "OUTROS SERVICOS DE TERCEIROS - PESSOA FISICA",
  "numero": "204900422 / 2014",
  "data": "18/03/2014",
  "historico": "Referente a locação de imovel destinado ao funcionamento do CAPS AD II NORTE - CENTRO DE ATENÇÃO PSICOSSOCIAL conforme contrato.",
  "itens": [
   {
    "descricao": "CONVERSAO",
    "quantidade": "1.00",
    "valor_unitario": "14.400,00",
    "valor_total": "14.400,00"
   }
  ]
 },
 {
  "instituicao": "PREFEITURA MUNICIPAL DO NATAL",
  "orgao": "SECRETARIA MUNICIPAL DE SAUDE",
  "credor": "000.000.000-00 - GUIOMAR DE ROCHA MEDEIROS",
  "empenhado": "R$ 4.151,75",
  "anulado": "R$ 0,00",
  "liquidado": "R$ 4.151,75",
  "pago": "R$ 0,00",
  "elemento": "OUTROS SERVICOS DE TERCEIROS - PESSOA FISICA",
  "numero": "204900066 / 2014",
  "data": "20/01/2014",
  "historico": "Locação de imóvel situado à Av. Paulistana, 2109, Conj. Panatis I, Natal. . Empenho feito conforme folha em anexo, contrato firmado 23/2013, repassado pelo Coordenadoria Administrativa Núcleo de Contratos.",
  "itens": [
   {
    "descricao": "CONVERSAO",
    "quantidade": "1.00",
    "valor_unitario": "4.151,75",
    "valor_total": "4.151,75"
   }
  ]
 },
 {
  "instituicao": "PREFEITURA MUNICIPAL DO NATAL",
  "orgao": "SECRETARIA MUNICIPAL DE SAUDE",
  "credor": "000.000.000-00 - HILMA TEIXEIRA DE FARIAS",
  "empenhado": "R$ 28.108,08",
  "anulado": "R$ 0,00",
  "liquidado": "R$ 0,00",
  "pago": "R$ 0,00",
  "elemento": "OUTROS SERVICOS DE TERCEIROS - PESSOA FISICA",
  "numero": "204901090 / 2014",
  "data": "16/09/2014",
  "historico": "O presente instrumento tem por objeto a locação do imóvel destinado ao funcionamento do serviço residencial terapêutico no Distrito Sanitário Leste, tipo II, conforme contrato firmado.",
  "itens": [
   {
    "descricao": "CONVERSAO",
    "quantidade": "1.00",
    "valor_unitario": "28.108,08",
    "valor_total": "28.108,08"
   }
  ]
 },
 {
  "instituicao": "PREFEITURA MUNICIPAL DO NATAL",
  "orgao": "SECRETARIA MUNICIPAL DE SAUDE",
  "credor": "08.241.747/0001-43 - PREFEITURA MUNICIPAL DE NATAL",
  "empenhado": "R$ 1.237.000,00",
  "anulado": "R$ 44.083,99",
  "liquidado": "R$ 1.192.916,01",
  "pago": "R$ 44.083,99",
  "elemento": "OUTRAS DESPESAS VARIAVEIS - PESSOAL CIVIL",
  "numero": "204900185 / 2014",
  "data": "31/01/2014",
  "historico": "O presente tem por objetivo as despesas variaveis, conforme memorando anexado nos autos a pagina 01, com origem do DGTES/SGRTS sendo esse assinado por sua Diretora. Valor empenhado conforme disponibilidade orçamentaria do momento.",
  "itens": [
   {
    "descricao": "CONVERSAO",
    "quantidade": "1.00",
    "valor_unitario": "1.237.000,00",
    "valor_total": "1.237.000,00"
   }
  ]
 },
 {
  "instituicao": "PREFEITURA MUNICIPAL DO NATAL",
  "orgao": "SECRETARIA MUNICIPAL DE SAUDE",
  "credor": "07.442.731/0001-36 - JMT SERVIÇOS E LOCAÇÃO DE MÃO DE OBRA LT",
  "empenhado": "R$ 29.000,00",
  "anulado": "R$ 0,00",
  "liquidado": "R$ 28.953,60",
  "pago": "R$ 0,00",
  "elemento": "Outras Despesas de Pessoal Decorrentes de Contrato",
  "numero": "204900223 / 2014",
  "data": "31/01/2014",
  "historico": "Referente a prestação de serviços de limpeza, conservação e higienização conforme contrato.",
  "itens": [
   {
    "descricao": "CONVERSAO",
    "quantidade": "1.00",
    "valor_unitario": "29.000,00",
    "valor_total": "29.000,00"
   }
  ]
 },
 {
  "instituicao": "PREFEITURA MUNICIPAL DO NATAL",
  "orgao": "SECRETARIA MUNICIPAL DE SAUDE",
  "credor": "07.442.731/0001-36 - JMT SERVIÇOS E LOCAÇÃO DE MÃO DE OBRA LT",
  "empenhado": "R$ 403.836,00",
  "anulado": "R$ 0,00",
  "liquidado": "R$ 403.836,00",
  "pago": "R$ 0,00",
  "elemento": "Outras Despesas de Pessoal Decorrentes de Contrato",
  "numero": "204900165 / 2014",
  "data": "20/01/2014",
  "historico": "Referente a prestação de serviços de limpeza, conservação e higienização hospitalar conforme contrato.",
  "itens": [
   {
    "descricao": "CONVERSAO",
    "quantidade": "1.00",
    "valor_unitario": "403.836,00",
    "valor_total": "403.836,00"
   }
  ]
 }
]